Workbook
Name InitialCapital: Config!$B$5

Sheet Config
A1: TradingAlgo Mosaic - Real DJ30 Rebalance Audit
A3: Market | B3: DJ30
A4: Benchmark | B4: DIA
A5: Initial capital | B5: 100000
A6: Universe size | B6: 30
A7: First week ending | B7: 2023-01-06
A8: Last week ending | B8: 2026-06-26
A9: Price convention | B9: last_price is the Friday closing price used for rebalance calculations.
A10: Execution convention | B10: Signals are calculated after Friday close; implementation is intended at next Monday open.
A11: User action | B11: Change Config!B5 to test a different starting capital.

Sheet Performance_Summary
A1: Performance Summary
A2: Aligned to published site performance window | B2: 2024-01-12 to 2026-06-26
A3: Market | B3: =Config!B3
A4: Benchmark | B4: =Config!B4
A5: Initial capital | B5: =InitialCapital
A6: Performance window start | B6: =DATEVALUE("2024-01-12")
A7: Performance window end | B7: =DATEVALUE("2026-06-26")
A8: Published weeks | B8: =COUNTIF(Equity_Line[published_window],TRUE)
A9: Portfolio final equity | B9: =InitialCapital*PRODUCT(1+FILTER(Equity_Line[weekly_return],Equity_Line[published_window]=TRUE))
A10: Benchmark final equity | B10: =InitialCapital*PRODUCT(1+FILTER(Equity_Line[benchmark_return],Equity_Line[published_window]=TRUE))
A11: Portfolio total return | B11: =B9/B5-1
A12: Benchmark total return | B12: =B10/B5-1
A13: Excess total return | B13: =B11-B12
A14: Portfolio CAGR | B14: 0.27964205
A15: Benchmark CAGR | B15: 0.15968623
A16: Annualized volatility | B16: =STDEV.S(FILTER(Equity_Line[weekly_return],Equity_Line[published_window]=TRUE))*SQRT(52)
A17: Benchmark annualized volatility | B17: =STDEV.S(FILTER(Equity_Line[benchmark_return],Equity_Line[published_window]=TRUE))*SQRT(52)
A18: Sharpe, rf 1% | B18: 1.422126
A19: Benchmark Sharpe, rf 0% | B19: 1.1786108
A20: Max drawdown | B20: -0.19614988
A21: Benchmark max drawdown | B21: -0.14288125
A22: Positive weeks | B22: =COUNTIF(FILTER(Equity_Line[weekly_return],Equity_Line[published_window]=TRUE),">0")
A23: Negative weeks | B23: =COUNTIF(FILTER(Equity_Line[weekly_return],Equity_Line[published_window]=TRUE),"<0")
A24: Win rate | B24: =IF((B23+B24)=0,0,B23/(B23+B24))
A25: Average weekly return | B25: =AVERAGE(FILTER(Equity_Line[weekly_return],Equity_Line[published_window]=TRUE))
A26: Best week | B26: =MAX(FILTER(Equity_Line[weekly_return],Equity_Line[published_window]=TRUE))
A27: Worst week | B27: =MIN(FILTER(Equity_Line[weekly_return],Equity_Line[published_window]=TRUE))
A28: Published site Strategy CAGR | B28: 0.27964205
A29: Published site Strategy MaxDD | B29: -0.19614988
A30: Published site Strategy Sharpe | B30: 1.422126
A31: Published site Bench CAGR | B31: 0.15968623
A32: Published site Bench MaxDD | B32: -0.14288125
A33: Published site Bench Sharpe | B33: 1.1786108
A36: Metric source note | B36: CAGR, Sharpe and MaxDD are aligned to reports_html/DJ30/report_data.json; final equity and total return remain linked to Config!B5.

Sheet Equity_Line
A1: WeekEnding | B1: portfolio_start_value | C1: portfolio_end_value | D1: weekly_return | E1: benchmark_return | F1: excess_return | G1: benchmark_equity | H1: drawdown | I1: benchmark_drawdown | J1: published_window
A2: =Weekly_Summary!B2 | B2: =Weekly_Summary!D2 | C2: =Weekly_Summary!E2 | D2: =Weekly_Summary!G2 | E2: =Weekly_Summary!I2 | F2: =Weekly_Summary!J2 | G2: =InitialCapital | H2: =C2/MAX($C$2:C2)-1 | I2: =G2/MAX($G$2:G2)-1 | J2: =AND(A2>=DATEVALUE("2024-01-12"),A2<=DATEVALUE("2026-06-26"))
A3: =Weekly_Summary!B3 | B3: =Weekly_Summary!D3 | C3: =Weekly_Summary!E3 | D3: =Weekly_Summary!G3 | E3: =Weekly_Summary!I3 | F3: =Weekly_Summary!J3 | G3: =G2*(1+E3) | H3: =C3/MAX($C$2:C3)-1 | I3: =G3/MAX($G$2:G3)-1 | J3: =AND(A3>=DATEVALUE("2024-01-12"),A3<=DATEVALUE("2026-06-26"))
A4: =Weekly_Summary!B4 | B4: =Weekly_Summary!D4 | C4: =Weekly_Summary!E4 | D4: =Weekly_Summary!G4 | E4: =Weekly_Summary!I4 | F4: =Weekly_Summary!J4 | G4: =G3*(1+E4) | H4: =C4/MAX($C$2:C4)-1 | I4: =G4/MAX($G$2:G4)-1 | J4: =AND(A4>=DATEVALUE("2024-01-12"),A4<=DATEVALUE("2026-06-26"))
A5: =Weekly_Summary!B5 | B5: =Weekly_Summary!D5 | C5: =Weekly_Summary!E5 | D5: =Weekly_Summary!G5 | E5: =Weekly_Summary!I5 | F5: =Weekly_Summary!J5 | G5: =G4*(1+E5) | H5: =C5/MAX($C$2:C5)-1 | I5: =G5/MAX($G$2:G5)-1 | J5: =AND(A5>=DATEVALUE("2024-01-12"),A5<=DATEVALUE("2026-06-26"))
A6: =Weekly_Summary!B6 | B6: =Weekly_Summary!D6 | C6: =Weekly_Summary!E6 | D6: =Weekly_Summary!G6 | E6: =Weekly_Summary!I6 | F6: =Weekly_Summary!J6 | G6: =G5*(1+E6) | H6: =C6/MAX($C$2:C6)-1 | I6: =G6/MAX($G$2:G6)-1 | J6: =AND(A6>=DATEVALUE("2024-01-12"),A6<=DATEVALUE("2026-06-26"))
A7: =Weekly_Summary!B7 | B7: =Weekly_Summary!D7 | C7: =Weekly_Summary!E7 | D7: =Weekly_Summary!G7 | E7: =Weekly_Summary!I7 | F7: =Weekly_Summary!J7 | G7: =G6*(1+E7) | H7: =C7/MAX($C$2:C7)-1 | I7: =G7/MAX($G$2:G7)-1 | J7: =AND(A7>=DATEVALUE("2024-01-12"),A7<=DATEVALUE("2026-06-26"))
A8: =Weekly_Summary!B8 | B8: =Weekly_Summary!D8 | C8: =Weekly_Summary!E8 | D8: =Weekly_Summary!G8 | E8: =Weekly_Summary!I8 | F8: =Weekly_Summary!J8 | G8: =G7*(1+E8) | H8: =C8/MAX($C$2:C8)-1 | I8: =G8/MAX($G$2:G8)-1 | J8: =AND(A8>=DATEVALUE("2024-01-12"),A8<=DATEVALUE("2026-06-26"))
A9: =Weekly_Summary!B9 | B9: =Weekly_Summary!D9 | C9: =Weekly_Summary!E9 | D9: =Weekly_Summary!G9 | E9: =Weekly_Summary!I9 | F9: =Weekly_Summary!J9 | G9: =G8*(1+E9) | H9: =C9/MAX($C$2:C9)-1 | I9: =G9/MAX($G$2:G9)-1 | J9: =AND(A9>=DATEVALUE("2024-01-12"),A9<=DATEVALUE("2026-06-26"))
A10: =Weekly_Summary!B10 | B10: =Weekly_Summary!D10 | C10: =Weekly_Summary!E10 | D10: =Weekly_Summary!G10 | E10: =Weekly_Summary!I10 | F10: =Weekly_Summary!J10 | G10: =G9*(1+E10) | H10: =C10/MAX($C$2:C10)-1 | I10: =G10/MAX($G$2:G10)-1 | J10: =AND(A10>=DATEVALUE("2024-01-12"),A10<=DATEVALUE("2026-06-26"))
A11: =Weekly_Summary!B11 | B11: =Weekly_Summary!D11 | C11: =Weekly_Summary!E11 | D11: =Weekly_Summary!G11 | E11: =Weekly_Summary!I11 | F11: =Weekly_Summary!J11 | G11: =G10*(1+E11) | H11: =C11/MAX($C$2:C11)-1 | I11: =G11/MAX($G$2:G11)-1 | J11: =AND(A11>=DATEVALUE("2024-01-12"),A11<=DATEVALUE("2026-06-26"))
A12: =Weekly_Summary!B12 | B12: =Weekly_Summary!D12 | C12: =Weekly_Summary!E12 | D12: =Weekly_Summary!G12 | E12: =Weekly_Summary!I12 | F12: =Weekly_Summary!J12 | G12: =G11*(1+E12) | H12: =C12/MAX($C$2:C12)-1 | I12: =G12/MAX($G$2:G12)-1 | J12: =AND(A12>=DATEVALUE("2024-01-12"),A12<=DATEVALUE("2026-06-26"))
A13: =Weekly_Summary!B13 | B13: =Weekly_Summary!D13 | C13: =Weekly_Summary!E13 | D13: =Weekly_Summary!G13 | E13: =Weekly_Summary!I13 | F13: =Weekly_Summary!J13 | G13: =G12*(1+E13) | H13: =C13/MAX($C$2:C13)-1 | I13: =G13/MAX($G$2:G13)-1 | J13: =AND(A13>=DATEVALUE("2024-01-12"),A13<=DATEVALUE("2026-06-26"))
A14: =Weekly_Summary!B14 | B14: =Weekly_Summary!D14 | C14: =Weekly_Summary!E14 | D14: =Weekly_Summary!G14 | E14: =Weekly_Summary!I14 | F14: =Weekly_Summary!J14 | G14: =G13*(1+E14) | H14: =C14/MAX($C$2:C14)-1 | I14: =G14/MAX($G$2:G14)-1 | J14: =AND(A14>=DATEVALUE("2024-01-12"),A14<=DATEVALUE("2026-06-26"))
... A183: =Weekly_Summary!B183 | B183: =Weekly_Summary!D183 | C183: =Weekly_Summary!E183 | D183: =Weekly_Summary!G183 | E183: =Weekly_Summary!I183 | F183: =Weekly_Summary!J183 | G183: =G182*(1+E183) | H183: =C183/MAX($C$2:C183)-1 | I183: =G183/MAX($G$2:G183)-1 | J183: =AND(A183>=DATEVALUE("2024-01-12"),A183<=DATEVALUE("2026-06-26"))

Sheet Weekly_Summary
A1: Market | B1: WeekEnding | C1: Benchmark | D1: portfolio_start_value | E1: portfolio_end_value | F1: weekly_pnl | G1: weekly_return | H1: strategy_return | I1: benchmark_return | J1: excess_return | K1: action | L1: in_tickers | M1: out_tickers | N1: selected_count
A2: DJ30 | B2: 2023-01-06 | C2: DIA | D2: =Rebalance_Audit!J32 | E2: =Rebalance_Audit!R32 | F2: =E2-D2 | G2: =IF(D2=0,0,F2/D2) | J2: =G2-I2 | K2: hold | N2: 0
A3: DJ30 | B3: 2023-01-13 | C3: DIA | D3: =Rebalance_Audit!J63 | E3: =Rebalance_Audit!R63 | F3: =E3-D3 | G3: =IF(D3=0,0,F3/D3) | H3: 0 | I3: 0.020102628 | J3: =G3-I3 | K3: hold | N3: 0
A4: DJ30 | B4: 2023-01-20 | C4: DIA | D4: =Rebalance_Audit!J94 | E4: =Rebalance_Audit!R94 | F4: =E4-D4 | G4: =IF(D4=0,0,F4/D4) | H4: 0 | I4: -0.026489999 | J4: =G4-I4 | K4: hold | N4: 0
A5: DJ30 | B5: 2023-01-27 | C5: DIA | D5: =Rebalance_Audit!J125 | E5: =Rebalance_Audit!R125 | F5: =E5-D5 | G5: =IF(D5=0,0,F5/D5) | H5: 0 | I5: 0.017801471 | J5: =G5-I5 | K5: hold | N5: 0
A6: DJ30 | B6: 2023-02-03 | C6: DIA | D6: =Rebalance_Audit!J156 | E6: =Rebalance_Audit!R156 | F6: =E6-D6 | G6: =IF(D6=0,0,F6/D6) | H6: 0 | I6: -0.0018549393 | J6: =G6-I6 | K6: hold | N6: 0
A7: DJ30 | B7: 2023-02-10 | C7: DIA | D7: =Rebalance_Audit!J187 | E7: =Rebalance_Audit!R187 | F7: =E7-D7 | G7: =IF(D7=0,0,F7/D7) | H7: 0 | I7: -0.00073737765 | J7: =G7-I7 | K7: hold | N7: 0
A8: DJ30 | B8: 2023-02-17 | C8: DIA | D8: =Rebalance_Audit!J218 | E8: =Rebalance_Audit!R218 | F8: =E8-D8 | G8: =IF(D8=0,0,F8/D8) | H8: 0 | I8: 0.00033766872 | J8: =G8-I8 | K8: hold | N8: 0
A9: DJ30 | B9: 2023-02-24 | C9: DIA | D9: =Rebalance_Audit!J249 | E9: =Rebalance_Audit!R249 | F9: =E9-D9 | G9: =IF(D9=0,0,F9/D9) | H9: 0 | I9: -0.030062717 | J9: =G9-I9 | K9: hold | N9: 0
A10: DJ30 | B10: 2023-03-03 | C10: DIA | D10: =Rebalance_Audit!J280 | E10: =Rebalance_Audit!R280 | F10: =E10-D10 | G10: =IF(D10=0,0,F10/D10) | H10: 0 | I10: 0.018559828 | J10: =G10-I10 | K10: hold | N10: 0
A11: DJ30 | B11: 2023-03-10 | C11: DIA | D11: =Rebalance_Audit!J311 | E11: =Rebalance_Audit!R311 | F11: =E11-D11 | G11: =IF(D11=0,0,F11/D11) | H11: 0 | I11: -0.043325805 | J11: =G11-I11 | K11: hold | N11: 0
A12: DJ30 | B12: 2023-03-17 | C12: DIA | D12: =Rebalance_Audit!J342 | E12: =Rebalance_Audit!R342 | F12: =E12-D12 | G12: =IF(D12=0,0,F12/D12) | H12: 0 | I12: -0.0011960564 | J12: =G12-I12 | K12: hold | N12: 0
A13: DJ30 | B13: 2023-03-24 | C13: DIA | D13: =Rebalance_Audit!J373 | E13: =Rebalance_Audit!R373 | F13: =E13-D13 | G13: =IF(D13=0,0,F13/D13) | H13: 0 | I13: 0.011993808 | J13: =G13-I13 | K13: hold | N13: 0
A14: DJ30 | B14: 2023-03-31 | C14: DIA | D14: =Rebalance_Audit!J404 | E14: =Rebalance_Audit!R404 | F14: =E14-D14 | G14: =IF(D14=0,0,F14/D14) | H14: 0 | I14: 0.031956004 | J14: =G14-I14 | K14: hold | N14: 0
A15: DJ30 | B15: 2023-04-07 | C15: DIA | D15: =Rebalance_Audit!J435 | E15: =Rebalance_Audit!R435 | F15: =E15-D15 | G15: =IF(D15=0,0,F15/D15) | H15: 0 | I15: 0.0068543459 | J15: =G15-I15 | K15: hold | N15: 0
A16: DJ30 | B16: 2023-04-14 | C16: DIA | D16: =Rebalance_Audit!J466 | E16: =Rebalance_Audit!R466 | F16: =E16-D16 | G16: =IF(D16=0,0,F16/D16) | H16: 0 | I16: 0.011764727 | J16: =G16-I16 | K16: hold | N16: 0
A17: DJ30 | B17: 2023-04-21 | C17: DIA | D17: =Rebalance_Audit!J497 | E17: =Rebalance_Audit!R497 | F17: =E17-D17 | G17: =IF(D17=0,0,F17/D17) | H17: 0 | I17: -0.0016106573 | J17: =G17-I17 | K17: hold | N17: 0
A18: DJ30 | B18: 2023-04-28 | C18: DIA | D18: =Rebalance_Audit!J528 | E18: =Rebalance_Audit!R528 | F18: =E18-D18 | G18: =IF(D18=0,0,F18/D18) | H18: 0 | I18: 0.0086361335 | J18: =G18-I18 | K18: hold | N18: 0
A19: DJ30 | B19: 2023-05-05 | C19: DIA | D19: =Rebalance_Audit!J559 | E19: =Rebalance_Audit!R559 | F19: =E19-D19 | G19: =IF(D19=0,0,F19/D19) | H19: 0 | I19: -0.012609105 | J19: =G19-I19 | K19: hold | N19: 0
A20: DJ30 | B20: 2023-05-12 | C20: DIA | D20: =Rebalance_Audit!J590 | E20: =Rebalance_Audit!R590 | F20: =E20-D20 | G20: =IF(D20=0,0,F20/D20) | H20: 0 | I20: -0.010482701 | J20: =G20-I20 | K20: hold | N20: 0
A21: DJ30 | B21: 2023-05-19 | C21: DIA | D21: =Rebalance_Audit!J621 | E21: =Rebalance_Audit!R621 | F21: =E21-D21 | G21: =IF(D21=0,0,F21/D21) | H21: 0 | I21: 0.005142405 | J21: =G21-I21 | K21: hold | N21: 0
A22: DJ30 | B22: 2023-05-26 | C22: DIA | D22: =Rebalance_Audit!J652 | E22: =Rebalance_Audit!R652 | F22: =E22-D22 | G22: =IF(D22=0,0,F22/D22) | H22: 0 | I22: -0.010024271 | J22: =G22-I22 | K22: hold | N22: 0
A23: DJ30 | B23: 2023-06-02 | C23: DIA | D23: =Rebalance_Audit!J683 | E23: =Rebalance_Audit!R683 | F23: =E23-D23 | G23: =IF(D23=0,0,F23/D23) | H23: 0 | I23: 0.021853463 | J23: =G23-I23 | K23: hold | N23: 0
A24: DJ30 | B24: 2023-06-09 | C24: DIA | D24: =Rebalance_Audit!J714 | E24: =Rebalance_Audit!R714 | F24: =E24-D24 | G24: =IF(D24=0,0,F24/D24) | H24: 0 | I24: 0.0035496151 | J24: =G24-I24 | K24: hold | N24: 0
A25: DJ30 | B25: 2023-06-16 | C25: DIA | D25: =Rebalance_Audit!J745 | E25: =Rebalance_Audit!R745 | F25: =E25-D25 | G25: =IF(D25=0,0,F25/D25) | H25: 0 | I25: 0.013127041 | J25: =G25-I25 | K25: hold | N25: 0
A26: DJ30 | B26: 2023-06-23 | C26: DIA | D26: =Rebalance_Audit!J776 | E26: =Rebalance_Audit!R776 | F26: =E26-D26 | G26: =IF(D26=0,0,F26/D26) | H26: 0 | I26: -0.016883069 | J26: =G26-I26 | K26: hold | N26: 0
A27: DJ30 | B27: 2023-06-30 | C27: DIA | D27: =Rebalance_Audit!J807 | E27: =Rebalance_Audit!R807 | F27: =E27-D27 | G27: =IF(D27=0,0,F27/D27) | H27: 0 | I27: 0.019842621 | J27: =G27-I27 | K27: hold | N27: 0
A28: DJ30 | B28: 2023-07-07 | C28: DIA | D28: =Rebalance_Audit!J838 | E28: =Rebalance_Audit!R838 | F28: =E28-D28 | G28: =IF(D28=0,0,F28/D28) | H28: 0 | I28: -0.018671128 | J28: =G28-I28 | K28: hold | N28: 0
A29: DJ30 | B29: 2023-07-14 | C29: DIA | D29: =Rebalance_Audit!J869 | E29: =Rebalance_Audit!R869 | F29: =E29-D29 | G29: =IF(D29=0,0,F29/D29) | H29: 0 | I29: 0.022938121 | J29: =G29-I29 | K29: hold | N29: 0
A30: DJ30 | B30: 2023-07-21 | C30: DIA | D30: =Rebalance_Audit!J900 | E30: =Rebalance_Audit!R900 | F30: =E30-D30 | G30: =IF(D30=0,0,F30/D30) | H30: 0 | I30: 0.020969381 | J30: =G30-I30 | K30: hold | N30: 0
A31: DJ30 | B31: 2023-07-28 | C31: DIA | D31: =Rebalance_Audit!J931 | E31: =Rebalance_Audit!R931 | F31: =E31-D31 | G31: =IF(D31=0,0,F31/D31) | H31: 0 | I31: 0.0066451963 | J31: =G31-I31 | K31: hold | N31: 0
A32: DJ30 | B32: 2023-08-04 | C32: DIA | D32: =Rebalance_Audit!J962 | E32: =Rebalance_Audit!R962 | F32: =E32-D32 | G32: =IF(D32=0,0,F32/D32) | H32: 0 | I32: -0.010804796 | J32: =G32-I32 | K32: hold | N32: 0
A33: DJ30 | B33: 2023-08-11 | C33: DIA | D33: =Rebalance_Audit!J993 | E33: =Rebalance_Audit!R993 | F33: =E33-D33 | G33: =IF(D33=0,0,F33/D33) | H33: 0 | I33: 0.0067015795 | J33: =G33-I33 | K33: hold | N33: 0
A34: DJ30 | B34: 2023-08-18 | C34: DIA | D34: =Rebalance_Audit!J1024 | E34: =Rebalance_Audit!R1024 | F34: =E34-D34 | G34: =IF(D34=0,0,F34/D34) | H34: 0 | I34: -0.020875357 | J34: =G34-I34 | K34: hold | N34: 0
A35: DJ30 | B35: 2023-08-25 | C35: DIA | D35: =Rebalance_Audit!J1055 | E35: =Rebalance_Audit!R1055 | F35: =E35-D35 | G35: =IF(D35=0,0,F35/D35) | H35: 0 | I35: -0.0046938781 | J35: =G35-I35 | K35: hold | N35: 0
A36: DJ30 | B36: 2023-09-01 | C36: DIA | D36: =Rebalance_Audit!J1086 | E36: =Rebalance_Audit!R1086 | F36: =E36-D36 | G36: =IF(D36=0,0,F36/D36) | H36: 0 | I36: 0.015953283 | J36: =G36-I36 | K36: hold | N36: 0
A37: DJ30 | B37: 2023-09-08 | C37: DIA | D37: =Rebalance_Audit!J1117 | E37: =Rebalance_Audit!R1117 | F37: =E37-D37 | G37: =IF(D37=0,0,F37/D37) | H37: 0 | I37: -0.0070778637 | J37: =G37-I37 | K37: hold | N37: 0
A38: DJ30 | B38: 2023-09-15 | C38: DIA | D38: =Rebalance_Audit!J1148 | E38: =Rebalance_Audit!R1148 | F38: =E38-D38 | G38: =IF(D38=0,0,F38/D38) | H38: 0 | I38: 0.0015741392 | J38: =G38-I38 | K38: hold | N38: 0
A39: DJ30 | B39: 2023-09-22 | C39: DIA | D39: =Rebalance_Audit!J1179 | E39: =Rebalance_Audit!R1179 | F39: =E39-D39 | G39: =IF(D39=0,0,F39/D39) | H39: 0 | I39: -0.018951896 | J39: =G39-I39 | K39: hold | N39: 0
A40: DJ30 | B40: 2023-09-29 | C40: DIA | D40: =Rebalance_Audit!J1210 | E40: =Rebalance_Audit!R1210 | F40: =E40-D40 | G40: =IF(D40=0,0,F40/D40) | H40: 0 | I40: -0.013634611 | J40: =G40-I40 | K40: hold | N40: 0
A41: DJ30 | B41: 2023-10-06 | C41: DIA | D41: =Rebalance_Audit!J1241 | E41: =Rebalance_Audit!R1241 | F41: =E41-D41 | G41: =IF(D41=0,0,F41/D41) | H41: 0 | I41: -0.0025376252 | J41: =G41-I41 | K41: hold | N41: 0
A42: DJ30 | B42: 2023-10-13 | C42: DIA | D42: =Rebalance_Audit!J1272 | E42: =Rebalance_Audit!R1272 | F42: =E42-D42 | G42: =IF(D42=0,0,F42/D42) | H42: 0 | I42: 0.0077220254 | J42: =G42-I42 | K42: hold | N42: 0
A43: DJ30 | B43: 2023-10-20 | C43: DIA | D43: =Rebalance_Audit!J1303 | E43: =Rebalance_Audit!R1303 | F43: =E43-D43 | G43: =IF(D43=0,0,F43/D43) | H43: 0 | I43: -0.015754968 | J43: =G43-I43 | K43: hold | N43: 0
A44: DJ30 | B44: 2023-10-27 | C44: DIA | D44: =Rebalance_Audit!J1334 | E44: =Rebalance_Audit!R1334 | F44: =E44-D44 | G44: =IF(D44=0,0,F44/D44) | H44: 0 | I44: -0.021136 | J44: =G44-I44 | K44: hold | N44: 0
A45: DJ30 | B45: 2023-11-03 | C45: DIA | D45: =Rebalance_Audit!J1365 | E45: =Rebalance_Audit!R1365 | F45: =E45-D45 | G45: =IF(D45=0,0,F45/D45) | H45: 0 | I45: 0.050649242 | J45: =G45-I45 | K45: hold | N45: 0
A46: DJ30 | B46: 2023-11-10 | C46: DIA | D46: =Rebalance_Audit!J1396 | E46: =Rebalance_Audit!R1396 | F46: =E46-D46 | G46: =IF(D46=0,0,F46/D46) | H46: 0 | I46: 0.0070462152 | J46: =G46-I46 | K46: hold | N46: 0
A47: DJ30 | B47: 2023-11-17 | C47: DIA | D47: =Rebalance_Audit!J1427 | E47: =Rebalance_Audit!R1427 | F47: =E47-D47 | G47: =IF(D47=0,0,F47/D47) | H47: 0 | I47: 0.020778282 | J47: =G47-I47 | K47: hold | N47: 0
A48: DJ30 | B48: 2023-11-24 | C48: DIA | D48: =Rebalance_Audit!J1458 | E48: =Rebalance_Audit!R1458 | F48: =E48-D48 | G48: =IF(D48=0,0,F48/D48) | H48: 0 | I48: 0.012506172 | J48: =G48-I48 | K48: hold | N48: 0
A49: DJ30 | B49: 2023-12-01 | C49: DIA | D49: =Rebalance_Audit!J1489 | E49: =Rebalance_Audit!R1489 | F49: =E49-D49 | G49: =IF(D49=0,0,F49/D49) | H49: 0 | I49: 0.026144682 | J49: =G49-I49 | K49: hold | N49: 0
A50: DJ30 | B50: 2023-12-08 | C50: DIA | D50: =Rebalance_Audit!J1520 | E50: =Rebalance_Audit!R1520 | F50: =E50-D50 | G50: =IF(D50=0,0,F50/D50) | H50: 0 | I50: 0.00019296156 | J50: =G50-I50 | K50: hold | N50: 0
A51: DJ30 | B51: 2023-12-15 | C51: DIA | D51: =Rebalance_Audit!J1551 | E51: =Rebalance_Audit!R1551 | F51: =E51-D51 | G51: =IF(D51=0,0,F51/D51) | H51: 0 | I51: 0.028484432 | J51: =G51-I51 | K51: hold | N51: 0
A52: DJ30 | B52: 2023-12-22 | C52: DIA | D52: =Rebalance_Audit!J1582 | E52: =Rebalance_Audit!R1582 | F52: =E52-D52 | G52: =IF(D52=0,0,F52/D52) | H52: 0 | I52: 0.0031397051 | J52: =G52-I52 | K52: hold | N52: 0
A53: DJ30 | B53: 2023-12-29 | C53: DIA | D53: =Rebalance_Audit!J1613 | E53: =Rebalance_Audit!R1613 | F53: =E53-D53 | G53: =IF(D53=0,0,F53/D53) | H53: 0 | I53: 0.0082128718 | J53: =G53-I53 | K53: hold | N53: 0
A54: DJ30 | B54: 2024-01-05 | C54: DIA | D54: =Rebalance_Audit!J1644 | E54: =Rebalance_Audit!R1644 | F54: =E54-D54 | G54: =IF(D54=0,0,F54/D54) | H54: -0.001 | I54: -0.0059168651 | J54: =G54-I54 | K54: rebalance | L54: NVDA|AMZN|CRM|IBM|JPM | N54: 5
A55: DJ30 | B55: 2024-01-12 | C55: DIA | D55: =Rebalance_Audit!J1675 | E55: =Rebalance_Audit!R1675 | F55: =E55-D55 | G55: =IF(D55=0,0,F55/D55) | H55: 0.056560755 | I55: 0.0033896253 | J55: =G55-I55 | K55: rebalance | L55: AMGN | M55: IBM | N55: 5
A56: DJ30 | B56: 2024-01-19 | C56: DIA | D56: =Rebalance_Audit!J1706 | E56: =Rebalance_Audit!R1706 | F56: =E56-D56 | G56: =IF(D56=0,0,F56/D56) | H56: 0.027330388 | I56: 0.007728735 | J56: =G56-I56 | K56: hold | N56: 5
A57: DJ30 | B57: 2024-01-26 | C57: DIA | D57: =Rebalance_Audit!J1737 | E57: =Rebalance_Audit!R1737 | F57: =E57-D57 | G57: =IF(D57=0,0,F57/D57) | H57: 0.013861099 | I57: 0.0065768526 | J57: =G57-I57 | K57: rebalance | L57: IBM | M57: AMZN | N57: 5
A58: DJ30 | B58: 2024-02-02 | C58: DIA | D58: =Rebalance_Audit!J1768 | E58: =Rebalance_Audit!R1768 | F58: =E58-D58 | G58: =IF(D58=0,0,F58/D58) | H58: 0.028925228 | I58: 0.01398624 | J58: =G58-I58 | K58: rebalance | L58: CAT | M58: JPM | N58: 5
A59: DJ30 | B59: 2024-02-09 | C59: DIA | D59: =Rebalance_Audit!J1799 | E59: =Rebalance_Audit!R1799 | F59: =E59-D59 | G59: =IF(D59=0,0,F59/D59) | H59: 0.0058937916 | I59: 0.00077627999 | J59: =G59-I59 | K59: hold | N59: 5
A60: DJ30 | B60: 2024-02-16 | C60: DIA | D60: =Rebalance_Audit!J1830 | E60: =Rebalance_Audit!R1830 | F60: =E60-D60 | G60: =IF(D60=0,0,F60/D60) | H60: 0.0010628261 | I60: 0.0002063331 | J60: =G60-I60 | K60: hold | N60: 5
A61: DJ30 | B61: 2024-02-23 | C61: DIA | D61: =Rebalance_Audit!J1861 | E61: =Rebalance_Audit!R1861 | F61: =E61-D61 | G61: =IF(D61=0,0,F61/D61) | H61: 0.022254722 | I61: 0.013180028 | J61: =G61-I61 | K61: hold | N61: 5
A62: DJ30 | B62: 2024-03-01 | C62: DIA | D62: =Rebalance_Audit!J1892 | E62: =Rebalance_Audit!R1892 | F62: =E62-D62 | G62: =IF(D62=0,0,F62/D62) | H62: 0.0296994 | I62: 7.6534846e-05 | J62: =G62-I62 | K62: hold | N62: 5
A63: DJ30 | B63: 2024-03-08 | C63: DIA | D63: =Rebalance_Audit!J1923 | E63: =Rebalance_Audit!R1923 | F63: =E63-D63 | G63: =IF(D63=0,0,F63/D63) | H63: 0.010468124 | I63: -0.0084843519 | J63: =G63-I63 | K63: hold | N63: 5
A64: DJ30 | B64: 2024-03-15 | C64: DIA | D64: =Rebalance_Audit!J1954 | E64: =Rebalance_Audit!R1954 | F64: =E64-D64 | G64: =IF(D64=0,0,F64/D64) | H64: -0.010174495 | I64: -0.00015983998 | J64: =G64-I64 | K64: hold | N64: 5
A65: DJ30 | B65: 2024-03-22 | C65: DIA | D65: =Rebalance_Audit!J1985 | E65: =Rebalance_Audit!R1985 | F65: =E65-D65 | G65: =IF(D65=0,0,F65/D65) | H65: 0.035434088 | I65: 0.019457196 | J65: =G65-I65 | K65: hold | N65: 5
A66: DJ30 | B66: 2024-03-29 | C66: DIA | D66: =Rebalance_Audit!J2016 | E66: =Rebalance_Audit!R2016 | F66: =E66-D66 | G66: =IF(D66=0,0,F66/D66) | H66: -0.0019503273 | I66: 0.0081868798 | J66: =G66-I66 | K66: hold | N66: 5
A67: DJ30 | B67: 2024-04-05 | C67: DIA | D67: =Rebalance_Audit!J2047 | E67: =Rebalance_Audit!R2047 | F67: =E67-D67 | G67: =IF(D67=0,0,F67/D67) | H67: -0.0097023364 | I67: -0.022375248 | J67: =G67-I67 | K67: hold | N67: 5
A68: DJ30 | B68: 2024-04-12 | C68: DIA | D68: =Rebalance_Audit!J2078 | E68: =Rebalance_Audit!R2078 | F68: =E68-D68 | G68: =IF(D68=0,0,F68/D68) | H68: -0.021074188 | I68: -0.02311914 | J68: =G68-I68 | K68: hold | N68: 5
A69: DJ30 | B69: 2024-04-19 | C69: DIA | D69: =Rebalance_Audit!J2109 | E69: =Rebalance_Audit!R2109 | F69: =E69-D69 | G69: =IF(D69=0,0,F69/D69) | H69: -0.048674095 | I69: 0.00034012991 | J69: =G69-I69 | K69: rebalance | L69: JPM | M69: AMGN | N69: 5
A70: DJ30 | B70: 2024-04-26 | C70: DIA | D70: =Rebalance_Audit!J2140 | E70: =Rebalance_Audit!R2140 | F70: =E70-D70 | G70: =IF(D70=0,0,F70/D70) | H70: 0.019176151 | I70: 0.0066088556 | J70: =G70-I70 | K70: hold | N70: 5
A71: DJ30 | B71: 2024-05-03 | C71: DIA | D71: =Rebalance_Audit!J2171 | E71: =Rebalance_Audit!R2171 | F71: =E71-D71 | G71: =IF(D71=0,0,F71/D71) | H71: -0.0066978184 | I71: 0.011665749 | J71: =G71-I71 | K71: hold | N71: 5
A72: DJ30 | B72: 2024-05-10 | C72: DIA | D72: =Rebalance_Audit!J2202 | E72: =Rebalance_Audit!R2202 | F72: =E72-D72 | G72: =IF(D72=0,0,F72/D72) | H72: 0.027779018 | I72: 0.021744311 | J72: =G72-I72 | K72: hold | N72: 5
A73: DJ30 | B73: 2024-05-17 | C73: DIA | D73: =Rebalance_Audit!J2233 | E73: =Rebalance_Audit!R2233 | F73: =E73-D73 | G73: =IF(D73=0,0,F73/D73) | H73: 0.021391411 | I73: 0.013578732 | J73: =G73-I73 | K73: hold | N73: 5
A74: DJ30 | B74: 2024-05-24 | C74: DIA | D74: =Rebalance_Audit!J2264 | E74: =Rebalance_Audit!R2264 | F74: =E74-D74 | G74: =IF(D74=0,0,F74/D74) | H74: 0.014607062 | I74: -0.023278126 | J74: =G74-I74 | K74: rebalance | L74: AMZN | M74: CRM | N74: 5
A75: DJ30 | B75: 2024-05-31 | C75: DIA | D75: =Rebalance_Audit!J2295 | E75: =Rebalance_Audit!R2295 | F75: =E75-D75 | G75: =IF(D75=0,0,F75/D75) | H75: -0.007590604 | I75: -0.0079612644 | J75: =G75-I75 | K75: hold | N75: 5
A76: DJ30 | B76: 2024-06-07 | C76: DIA | D76: =Rebalance_Audit!J2326 | E76: =Rebalance_Audit!R2326 | F76: =E76-D76 | G76: =IF(D76=0,0,F76/D76) | H76: 0.023724358 | I76: 0.002477163 | J76: =G76-I76 | K76: rebalance | L76: AXP|GS|TRV | M76: AMZN|JPM|IBM | N76: 5
A77: DJ30 | B77: 2024-06-14 | C77: DIA | D77: =Rebalance_Audit!J2357 | E77: =Rebalance_Audit!R2357 | F77: =E77-D77 | G77: =IF(D77=0,0,F77/D77) | H77: -0.0025116049 | I77: -0.0052253515 | J77: =G77-I77 | K77: hold | N77: 5
A78: DJ30 | B78: 2024-06-21 | C78: DIA | D78: =Rebalance_Audit!J2388 | E78: =Rebalance_Audit!R2388 | F78: =E78-D78 | G78: =IF(D78=0,0,F78/D78) | H78: 0.0059606904 | I78: 0.014889925 | J78: =G78-I78 | K78: rebalance | L78: AMZN | M78: CAT | N78: 5
A79: DJ30 | B79: 2024-06-28 | C79: DIA | D79: =Rebalance_Audit!J2419 | E79: =Rebalance_Audit!R2419 | F79: =E79-D79 | G79: =IF(D79=0,0,F79/D79) | H79: -0.0045688142 | I79: -0.00053662172 | J79: =G79-I79 | K79: hold | N79: 5
A80: DJ30 | B80: 2024-07-05 | C80: DIA | D80: =Rebalance_Audit!J2450 | E80: =Rebalance_Audit!R2450 | F80: =E80-D80 | G80: =IF(D80=0,0,F80/D80) | H80: 0.018873599 | I80: 0.0065708878 | J80: =G80-I80 | K80: hold | N80: 5
A81: DJ30 | B81: 2024-07-12 | C81: DIA | D81: =Rebalance_Audit!J2481 | E81: =Rebalance_Audit!R2481 | F81: =E81-D81 | G81: =IF(D81=0,0,F81/D81) | H81: 0.01860725 | I81: 0.016814608 | J81: =G81-I81 | K81: hold | N81: 5
A82: DJ30 | B82: 2024-07-19 | C82: DIA | D82: =Rebalance_Audit!J2512 | E82: =Rebalance_Audit!R2512 | F82: =E82-D82 | G82: =IF(D82=0,0,F82/D82) | H82: -0.032011365 | I82: 0.0070502357 | J82: =G82-I82 | K82: rebalance | L82: VZ | M82: GS | N82: 5
A83: DJ30 | B83: 2024-07-26 | C83: DIA | D83: =Rebalance_Audit!J2543 | E83: =Rebalance_Audit!R2543 | F83: =E83-D83 | G83: =IF(D83=0,0,F83/D83) | H83: -0.003210492 | I83: 0.0074946937 | J83: =G83-I83 | K83: hold | N83: 5
A84: DJ30 | B84: 2024-08-02 | C84: DIA | D84: =Rebalance_Audit!J2574 | E84: =Rebalance_Audit!R2574 | F84: =E84-D84 | G84: =IF(D84=0,0,F84/D84) | H84: -0.032686261 | I84: -0.02177514 | J84: =G84-I84 | K84: rebalance | L84: WMT | M84: VZ | N84: 5
A85: DJ30 | B85: 2024-08-09 | C85: DIA | D85: =Rebalance_Audit!J2605 | E85: =Rebalance_Audit!R2605 | F85: =E85-D85 | G85: =IF(D85=0,0,F85/D85) | H85: -0.0048470863 | I85: -0.0049856502 | J85: =G85-I85 | K85: rebalance | L85: MMM | M85: TRV | N85: 5
A86: DJ30 | B86: 2024-08-16 | C86: DIA | D86: =Rebalance_Audit!J2636 | E86: =Rebalance_Audit!R2636 | F86: =E86-D86 | G86: =IF(D86=0,0,F86/D86) | H86: 0.082683507 | I86: 0.030160616 | J86: =G86-I86 | K86: rebalance | L86: VZ | M86: AMZN | N86: 5
A87: DJ30 | B87: 2024-08-23 | C87: DIA | D87: =Rebalance_Audit!J2667 | E87: =Rebalance_Audit!R2667 | F87: =E87-D87 | G87: =IF(D87=0,0,F87/D87) | H87: 0.021955267 | I87: 0.012514001 | J87: =G87-I87 | K87: hold | N87: 5
A88: DJ30 | B88: 2024-08-30 | C88: DIA | D88: =Rebalance_Audit!J2698 | E88: =Rebalance_Audit!R2698 | F88: =E88-D88 | G88: =IF(D88=0,0,F88/D88) | H88: 0.0046534162 | I88: 0.010635563 | J88: =G88-I88 | K88: hold | N88: 5
A89: DJ30 | B89: 2024-09-06 | C89: DIA | D89: =Rebalance_Audit!J2729 | E89: =Rebalance_Audit!R2729 | F89: =E89-D89 | G89: =IF(D89=0,0,F89/D89) | H89: -0.052980502 | I89: -0.028207008 | J89: =G89-I89 | K89: rebalance | L89: TRV | M89: VZ | N89: 5
A90: DJ30 | B90: 2024-09-13 | C90: DIA | D90: =Rebalance_Audit!J2760 | E90: =Rebalance_Audit!R2760 | F90: =E90-D90 | G90: =IF(D90=0,0,F90/D90) | H90: 0.064326127 | I90: 0.025885917 | J90: =G90-I90 | K90: rebalance | L90: KO|IBM | M90: WMT|TRV | N90: 5
A91: DJ30 | B91: 2024-09-20 | C91: DIA | D91: =Rebalance_Audit!J2791 | E91: =Rebalance_Audit!R2791 | F91: =E91-D91 | G91: =IF(D91=0,0,F91/D91) | H91: 0.0082500968 | I91: 0.016578915 | J91: =G91-I91 | K91: hold | N91: 5
A92: DJ30 | B92: 2024-09-27 | C92: DIA | D92: =Rebalance_Audit!J2822 | E92: =Rebalance_Audit!R2822 | F92: =E92-D92 | G92: =IF(D92=0,0,F92/D92) | H92: 0.017907437 | I92: 0.0056589082 | J92: =G92-I92 | K92: hold | N92: 5
A93: DJ30 | B93: 2024-10-04 | C93: DIA | D93: =Rebalance_Audit!J2853 | E93: =Rebalance_Audit!R2853 | F93: =E93-D93 | G93: =IF(D93=0,0,F93/D93) | H93: 0.0071567998 | I93: 0.0010874669 | J93: =G93-I93 | K93: hold | N93: 5
A94: DJ30 | B94: 2024-10-11 | C94: DIA | D94: =Rebalance_Audit!J2884 | E94: =Rebalance_Audit!R2884 | F94: =E94-D94 | G94: =IF(D94=0,0,F94/D94) | H94: 0.019501571 | I94: 0.012564726 | J94: =G94-I94 | K94: rebalance | L94: WMT | M94: IBM | N94: 5
A95: DJ30 | B95: 2024-10-18 | C95: DIA | D95: =Rebalance_Audit!J2915 | E95: =Rebalance_Audit!R2915 | F95: =E95-D95 | G95: =IF(D95=0,0,F95/D95) | H95: 0.010905192 | I95: 0.0094678632 | J95: =G95-I95 | K95: rebalance | L95: TRV | M95: WMT | N95: 5
A96: DJ30 | B96: 2024-10-25 | C96: DIA | D96: =Rebalance_Audit!J2946 | E96: =Rebalance_Audit!R2946 | F96: =E96-D96 | G96: =IF(D96=0,0,F96/D96) | H96: -0.03872546 | I96: -0.026581063 | J96: =G96-I96 | K96: rebalance | L96: PG | M96: KO | N96: 5
A97: DJ30 | B97: 2024-11-01 | C97: DIA | D97: =Rebalance_Audit!J2977 | E97: =Rebalance_Audit!R2977 | F97: =E97-D97 | G97: =IF(D97=0,0,F97/D97) | H97: -0.0091110561 | I97: -0.0017095604 | J97: =G97-I97 | K97: rebalance | L97: GS|KO | M97: AXP|PG | N97: 5
A98: DJ30 | B98: 2024-11-08 | C98: DIA | D98: =Rebalance_Audit!J3008 | E98: =Rebalance_Audit!R3008 | F98: =E98-D98 | G98: =IF(D98=0,0,F98/D98) | H98: 0.061986724 | I98: 0.046834193 | J98: =G98-I98 | K98: hold | N98: 5
A99: DJ30 | B99: 2024-11-15 | C99: DIA | D99: =Rebalance_Audit!J3039 | E99: =Rebalance_Audit!R3039 | F99: =E99-D99 | G99: =IF(D99=0,0,F99/D99) | H99: -0.015709149 | I99: -0.012123874 | J99: =G99-I99 | K99: hold | N99: 5
A100: DJ30 | B100: 2024-11-22 | C100: DIA | D100: =Rebalance_Audit!J3070 | E100: =Rebalance_Audit!R3070 | F100: =E100-D100 | G100: =IF(D100=0,0,F100/D100) | H100: 0.0088872575 | I100: 0.019907506 | J100: =G100-I100 | K100: rebalance | L100: IBM | M100: KO | N100: 5
...

Sheet Rebalance_Audit
A1: Market | B1: WeekEnding | C1: Benchmark | D1: Asset | E1: Company | F1: Sector | G1: last_price | H1: position_before | I1: qty_before | J1: value_before | K1: weight_before | L1: Status | M1: target_weight | N1: value_change | O1: qty_change | P1: position_after | Q1: qty_after | R1: value_after | S1: weight_after | T1: strategy_return | U1: benchmark_return | V1: notes
A2: DJ30 | B2: 2023-01-06 | C2: DIA | D2: AAPL | E2: AAPL | F2: - | G2: 127.45676 | I2: =IF(M2>0,InitialCapital/5/G2,0) | J2: =I2*G2 | K2: =IF($J$32=0,0,J2/$J$32) | L2: REJECTED | M2: 0 | N2: =M2*$J$32-J2 | O2: =IF(G2=0,0,N2/G2) | P2: =IF(M2>0,D2,"") | Q2: =I2+O2 | R2: =Q2*G2 | S2: =IF($R$32=0,0,R2/$R$32) | V2: not in initial selection
A3: DJ30 | B3: 2023-01-06 | C3: DIA | D3: AMGN | E3: AMGN | F3: - | G3: 246.45937 | I3: =IF(M3>0,InitialCapital/5/G3,0) | J3: =I3*G3 | K3: =IF($J$32=0,0,J3/$J$32) | L3: REJECTED | M3: 0 | N3: =M3*$J$32-J3 | O3: =IF(G3=0,0,N3/G3) | P3: =IF(M3>0,D3,"") | Q3: =I3+O3 | R3: =Q3*G3 | S3: =IF($R$32=0,0,R3/$R$32) | V3: not in initial selection
A4: DJ30 | B4: 2023-01-06 | C4: DIA | D4: AMZN | E4: AMZN | F4: - | G4: 86.080002 | I4: =IF(M4>0,InitialCapital/5/G4,0) | J4: =I4*G4 | K4: =IF($J$32=0,0,J4/$J$32) | L4: REJECTED | M4: 0 | N4: =M4*$J$32-J4 | O4: =IF(G4=0,0,N4/G4) | P4: =IF(M4>0,D4,"") | Q4: =I4+O4 | R4: =Q4*G4 | S4: =IF($R$32=0,0,R4/$R$32) | V4: not in initial selection
A5: DJ30 | B5: 2023-01-06 | C5: DIA | D5: AXP | E5: AXP | F5: - | G5: 144.39514 | I5: =IF(M5>0,InitialCapital/5/G5,0) | J5: =I5*G5 | K5: =IF($J$32=0,0,J5/$J$32) | L5: REJECTED | M5: 0 | N5: =M5*$J$32-J5 | O5: =IF(G5=0,0,N5/G5) | P5: =IF(M5>0,D5,"") | Q5: =I5+O5 | R5: =Q5*G5 | S5: =IF($R$32=0,0,R5/$R$32) | V5: not in initial selection
A6: DJ30 | B6: 2023-01-06 | C6: DIA | D6: BA | E6: BA | F6: - | G6: 213 | I6: =IF(M6>0,InitialCapital/5/G6,0) | J6: =I6*G6 | K6: =IF($J$32=0,0,J6/$J$32) | L6: REJECTED | M6: 0 | N6: =M6*$J$32-J6 | O6: =IF(G6=0,0,N6/G6) | P6: =IF(M6>0,D6,"") | Q6: =I6+O6 | R6: =Q6*G6 | S6: =IF($R$32=0,0,R6/$R$32) | V6: not in initial selection
A7: DJ30 | B7: 2023-01-06 | C7: DIA | D7: CAT | E7: CAT | F7: - | G7: 235.4472 | I7: =IF(M7>0,InitialCapital/5/G7,0) | J7: =I7*G7 | K7: =IF($J$32=0,0,J7/$J$32) | L7: REJECTED | M7: 0 | N7: =M7*$J$32-J7 | O7: =IF(G7=0,0,N7/G7) | P7: =IF(M7>0,D7,"") | Q7: =I7+O7 | R7: =Q7*G7 | S7: =IF($R$32=0,0,R7/$R$32) | V7: not in initial selection
A8: DJ30 | B8: 2023-01-06 | C8: DIA | D8: CRM | E8: CRM | F8: - | G8: 138.12045 | I8: =IF(M8>0,InitialCapital/5/G8,0) | J8: =I8*G8 | K8: =IF($J$32=0,0,J8/$J$32) | L8: REJECTED | M8: 0 | N8: =M8*$J$32-J8 | O8: =IF(G8=0,0,N8/G8) | P8: =IF(M8>0,D8,"") | Q8: =I8+O8 | R8: =Q8*G8 | S8: =IF($R$32=0,0,R8/$R$32) | V8: not in initial selection
A9: DJ30 | B9: 2023-01-06 | C9: DIA | D9: CSCO | E9: CSCO | F9: - | G9: 44.140488 | I9: =IF(M9>0,InitialCapital/5/G9,0) | J9: =I9*G9 | K9: =IF($J$32=0,0,J9/$J$32) | L9: REJECTED | M9: 0 | N9: =M9*$J$32-J9 | O9: =IF(G9=0,0,N9/G9) | P9: =IF(M9>0,D9,"") | Q9: =I9+O9 | R9: =Q9*G9 | S9: =IF($R$32=0,0,R9/$R$32) | V9: not in initial selection
A10: DJ30 | B10: 2023-01-06 | C10: DIA | D10: CVX | E10: CVX | F10: - | G10: 152.746 | I10: =IF(M10>0,InitialCapital/5/G10,0) | J10: =I10*G10 | K10: =IF($J$32=0,0,J10/$J$32) | L10: REJECTED | M10: 0 | N10: =M10*$J$32-J10 | O10: =IF(G10=0,0,N10/G10) | P10: =IF(M10>0,D10,"") | Q10: =I10+O10 | R10: =Q10*G10 | S10: =IF($R$32=0,0,R10/$R$32) | V10: not in initial selection
A11: DJ30 | B11: 2023-01-06 | C11: DIA | D11: DIS | E11: DIS | F11: - | G11: 91.759125 | I11: =IF(M11>0,InitialCapital/5/G11,0) | J11: =I11*G11 | K11: =IF($J$32=0,0,J11/$J$32) | L11: REJECTED | M11: 0 | N11: =M11*$J$32-J11 | O11: =IF(G11=0,0,N11/G11) | P11: =IF(M11>0,D11,"") | Q11: =I11+O11 | R11: =Q11*G11 | S11: =IF($R$32=0,0,R11/$R$32) | V11: not in initial selection
A12: DJ30 | B12: 2023-01-06 | C12: DIA | D12: GS | E12: GS | F12: - | G12: 319.72012 | I12: =IF(M12>0,InitialCapital/5/G12,0) | J12: =I12*G12 | K12: =IF($J$32=0,0,J12/$J$32) | L12: REJECTED | M12: 0 | N12: =M12*$J$32-J12 | O12: =IF(G12=0,0,N12/G12) | P12: =IF(M12>0,D12,"") | Q12: =I12+O12 | R12: =Q12*G12 | S12: =IF($R$32=0,0,R12/$R$32) | V12: not in initial selection
A13: DJ30 | B13: 2023-01-06 | C13: DIA | D13: HD | E13: HD | F13: - | G13: 290.08255 | I13: =IF(M13>0,InitialCapital/5/G13,0) | J13: =I13*G13 | K13: =IF($J$32=0,0,J13/$J$32) | L13: REJECTED | M13: 0 | N13: =M13*$J$32-J13 | O13: =IF(G13=0,0,N13/G13) | P13: =IF(M13>0,D13,"") | Q13: =I13+O13 | R13: =Q13*G13 | S13: =IF($R$32=0,0,R13/$R$32) | V13: not in initial selection
... A31: DJ30 | B31: 2023-01-06 | C31: DIA | D31: WMT | E31: WMT | F31: - | G31: 46.983047 | I31: =IF(M31>0,InitialCapital/5/G31,0) | J31: =I31*G31 | K31: =IF($J$32=0,0,J31/$J$32) | L31: REJECTED | M31: 0 | N31: =M31*$J$32-J31 | O31: =IF(G31=0,0,N31/G31) | P31: =IF(M31>0,D31,"") | Q31: =I31+O31 | R31: =Q31*G31 | S31: =IF($R$32=0,0,R31/$R$32) | V31: not in initial selection
A32: DJ30 | B32: 2023-01-06 | C32: DIA | D32: Tot Portfolio | J32: =SUM(J2:J31) | K32: =SUM(K2:K31) | L32: TOTAL | M32: =SUM(M2:M31) | N32: =SUM(N2:N31) | O32: =SUM(O2:O31) | R32: =SUM(R2:R31) | S32: =SUM(S2:S31)
A33: DJ30 | B33: 2023-01-13 | C33: DIA | D33: AAPL | E33: AAPL | F33: - | G33: 132.511 | H33: =P2 | I33: =Q2 | J33: =I33*G33 | K33: =IF($J$63=0,0,J33/$J$63) | L33: REJECTED | M33: 0 | N33: =M33*$J$63-J33 | O33: =IF(G33=0,0,N33/G33) | P33: =IF(M33>0,D33,"") | Q33: =I33+O33 | R33: =Q33*G33 | S33: =IF($R$63=0,0,R33/$R$63) | T33: 0 | U33: 0.020102628 | V33: not selected
A34: DJ30 | B34: 2023-01-13 | C34: DIA | D34: AMGN | E34: AMGN | F34: - | G34: 243.35172 | H34: =P3 | I34: =Q3 | J34: =I34*G34 | K34: =IF($J$63=0,0,J34/$J$63) | L34: REJECTED | M34: 0 | N34: =M34*$J$63-J34 | O34: =IF(G34=0,0,N34/G34) | P34: =IF(M34>0,D34,"") | Q34: =I34+O34 | R34: =Q34*G34 | S34: =IF($R$63=0,0,R34/$R$63) | T34: 0 | U34: 0.020102628 | V34: not selected
A35: DJ30 | B35: 2023-01-13 | C35: DIA | D35: AMZN | E35: AMZN | F35: - | G35: 98.120003 | H35: =P4 | I35: =Q4 | J35: =I35*G35 | K35: =IF($J$63=0,0,J35/$J$63) | L35: REJECTED | M35: 0 | N35: =M35*$J$63-J35 | O35: =IF(G35=0,0,N35/G35) | P35: =IF(M35>0,D35,"") | Q35: =I35+O35 | R35: =Q35*G35 | S35: =IF($R$63=0,0,R35/$R$63) | T35: 0 | U35: 0.020102628 | V35: not selected
A36: DJ30 | B36: 2023-01-13 | C36: DIA | D36: AXP | E36: AXP | F36: - | G36: 149.77017 | H36: =P5 | I36: =Q5 | J36: =I36*G36 | K36: =IF($J$63=0,0,J36/$J$63) | L36: REJECTED | M36: 0 | N36: =M36*$J$63-J36 | O36: =IF(G36=0,0,N36/G36) | P36: =IF(M36>0,D36,"") | Q36: =I36+O36 | R36: =Q36*G36 | S36: =IF($R$63=0,0,R36/$R$63) | T36: 0 | U36: 0.020102628 | V36: not selected
A37: DJ30 | B37: 2023-01-13 | C37: DIA | D37: BA | E37: BA | F37: - | G37: 214.13 | H37: =P6 | I37: =Q6 | J37: =I37*G37 | K37: =IF($J$63=0,0,J37/$J$63) | L37: REJECTED | M37: 0 | N37: =M37*$J$63-J37 | O37: =IF(G37=0,0,N37/G37) | P37: =IF(M37>0,D37,"") | Q37: =I37+O37 | R37: =Q37*G37 | S37: =IF($R$63=0,0,R37/$R$63) | T37: 0 | U37: 0.020102628 | V37: not selected
A38: DJ30 | B38: 2023-01-13 | C38: DIA | D38: CAT | E38: CAT | F38: - | G38: 244.5298 | H38: =P7 | I38: =Q7 | J38: =I38*G38 | K38: =IF($J$63=0,0,J38/$J$63) | L38: REJECTED | M38: 0 | N38: =M38*$J$63-J38 | O38: =IF(G38=0,0,N38/G38) | P38: =IF(M38>0,D38,"") | Q38: =I38+O38 | R38: =Q38*G38 | S38: =IF($R$63=0,0,R38/$R$63) | T38: 0 | U38: 0.020102628 | V38: not selected
A39: DJ30 | B39: 2023-01-13 | C39: DIA | D39: CRM | E39: CRM | F39: - | G39: 146.96739 | H39: =P8 | I39: =Q8 | J39: =I39*G39 | K39: =IF($J$63=0,0,J39/$J$63) | L39: REJECTED | M39: 0 | N39: =M39*$J$63-J39 | O39: =IF(G39=0,0,N39/G39) | P39: =IF(M39>0,D39,"") | Q39: =I39+O39 | R39: =Q39*G39 | S39: =IF($R$63=0,0,R39/$R$63) | T39: 0 | U39: 0.020102628 | V39: not selected
A40: DJ30 | B40: 2023-01-13 | C40: DIA | D40: CSCO | E40: CSCO | F40: - | G40: 44.652054 | H40: =P9 | I40: =Q9 | J40: =I40*G40 | K40: =IF($J$63=0,0,J40/$J$63) | L40: REJECTED | M40: 0 | N40: =M40*$J$63-J40 | O40: =IF(G40=0,0,N40/G40) | P40: =IF(M40>0,D40,"") | Q40: =I40+O40 | R40: =Q40*G40 | S40: =IF($R$63=0,0,R40/$R$63) | T40: 0 | U40: 0.020102628 | V40: not selected
A41: DJ30 | B41: 2023-01-13 | C41: DIA | D41: CVX | E41: CVX | F41: - | G41: 153.61111 | H41: =P10 | I41: =Q10 | J41: =I41*G41 | K41: =IF($J$63=0,0,J41/$J$63) | L41: REJECTED | M41: 0 | N41: =M41*$J$63-J41 | O41: =IF(G41=0,0,N41/G41) | P41: =IF(M41>0,D41,"") | Q41: =I41+O41 | R41: =Q41*G41 | S41: =IF($R$63=0,0,R41/$R$63) | T41: 0 | U41: 0.020102628 | V41: not selected
A42: DJ30 | B42: 2023-01-13 | C42: DIA | D42: DIS | E42: DIS | F42: - | G42: 97.113052 | H42: =P11 | I42: =Q11 | J42: =I42*G42 | K42: =IF($J$63=0,0,J42/$J$63) | L42: REJECTED | M42: 0 | N42: =M42*$J$63-J42 | O42: =IF(G42=0,0,N42/G42) | P42: =IF(M42>0,D42,"") | Q42: =I42+O42 | R42: =Q42*G42 | S42: =IF($R$63=0,0,R42/$R$63) | T42: 0 | U42: 0.020102628 | V42: not selected
A43: DJ30 | B43: 2023-01-13 | C43: DIA | D43: GS | E43: GS | F43: - | G43: 343.52829 | H43: =P12 | I43: =Q12 | J43: =I43*G43 | K43: =IF($J$63=0,0,J43/$J$63) | L43: REJECTED | M43: 0 | N43: =M43*$J$63-J43 | O43: =IF(G43=0,0,N43/G43) | P43: =IF(M43>0,D43,"") | Q43: =I43+O43 | R43: =Q43*G43 | S43: =IF($R$63=0,0,R43/$R$63) | T43: 0 | U43: 0.020102628 | V43: not selected
A44: DJ30 | B44: 2023-01-13 | C44: DIA | D44: HD | E44: HD | F44: - | G44: 302.58008 | H44: =P13 | I44: =Q13 | J44: =I44*G44 | K44: =IF($J$63=0,0,J44/$J$63) | L44: REJECTED | M44: 0 | N44: =M44*$J$63-J44 | O44: =IF(G44=0,0,N44/G44) | P44: =IF(M44>0,D44,"") | Q44: =I44+O44 | R44: =Q44*G44 | S44: =IF($R$63=0,0,R44/$R$63) | T44: 0 | U44: 0.020102628 | V44: not selected
... A62: DJ30 | B62: 2023-01-13 | C62: DIA | D62: WMT | E62: WMT | F62: - | G62: 46.506111 | H62: =P31 | I62: =Q31 | J62: =I62*G62 | K62: =IF($J$63=0,0,J62/$J$63) | L62: REJECTED | M62: 0 | N62: =M62*$J$63-J62 | O62: =IF(G62=0,0,N62/G62) | P62: =IF(M62>0,D62,"") | Q62: =I62+O62 | R62: =Q62*G62 | S62: =IF($R$63=0,0,R62/$R$63) | T62: 0 | U62: 0.020102628 | V62: not selected
A63: DJ30 | B63: 2023-01-13 | C63: DIA | D63: Tot Portfolio | J63: =SUM(J33:J62) | K63: =SUM(K33:K62) | L63: TOTAL | M63: =SUM(M33:M62) | N63: =SUM(N33:N62) | O63: =SUM(O33:O62) | R63: =SUM(R33:R62) | S63: =SUM(S33:S62) | T63: 0 | U63: 0.020102628
A64: DJ30 | B64: 2023-01-20 | C64: DIA | D64: AAPL | E64: AAPL | F64: - | G64: 135.56909 | H64: =P33 | I64: =Q33 | J64: =I64*G64 | K64: =IF($J$94=0,0,J64/$J$94) | L64: REJECTED | M64: 0 | N64: =M64*$J$94-J64 | O64: =IF(G64=0,0,N64/G64) | P64: =IF(M64>0,D64,"") | Q64: =I64+O64 | R64: =Q64*G64 | S64: =IF($R$94=0,0,R64/$R$94) | T64: 0 | U64: -0.026489999 | V64: not selected
A65: DJ30 | B65: 2023-01-20 | C65: DIA | D65: AMGN | E65: AMGN | F65: - | G65: 235.74838 | H65: =P34 | I65: =Q34 | J65: =I65*G65 | K65: =IF($J$94=0,0,J65/$J$94) | L65: REJECTED | M65: 0 | N65: =M65*$J$94-J65 | O65: =IF(G65=0,0,N65/G65) | P65: =IF(M65>0,D65,"") | Q65: =I65+O65 | R65: =Q65*G65 | S65: =IF($R$94=0,0,R65/$R$94) | T65: 0 | U65: -0.026489999 | V65: not selected
A66: DJ30 | B66: 2023-01-20 | C66: DIA | D66: AMZN | E66: AMZN | F66: - | G66: 97.25 | H66: =P35 | I66: =Q35 | J66: =I66*G66 | K66: =IF($J$94=0,0,J66/$J$94) | L66: REJECTED | M66: 0 | N66: =M66*$J$94-J66 | O66: =IF(G66=0,0,N66/G66) | P66: =IF(M66>0,D66,"") | Q66: =I66+O66 | R66: =Q66*G66 | S66: =IF($R$94=0,0,R66/$R$94) | T66: 0 | U66: -0.026489999 | V66: not selected
A67: DJ30 | B67: 2023-01-20 | C67: DIA | D67: AXP | E67: AXP | F67: - | G67: 145.77016 | H67: =P36 | I67: =Q36 | J67: =I67*G67 | K67: =IF($J$94=0,0,J67/$J$94) | L67: REJECTED | M67: 0 | N67: =M67*$J$94-J67 | O67: =IF(G67=0,0,N67/G67) | P67: =IF(M67>0,D67,"") | Q67: =I67+O67 | R67: =Q67*G67 | S67: =IF($R$94=0,0,R67/$R$94) | T67: 0 | U67: -0.026489999 | V67: not selected
A68: DJ30 | B68: 2023-01-20 | C68: DIA | D68: BA | E68: BA | F68: - | G68: 206.75999 | H68: =P37 | I68: =Q37 | J68: =I68*G68 | K68: =IF($J$94=0,0,J68/$J$94) | L68: REJECTED | M68: 0 | N68: =M68*$J$94-J68 | O68: =IF(G68=0,0,N68/G68) | P68: =IF(M68>0,D68,"") | Q68: =I68+O68 | R68: =Q68*G68 | S68: =IF($R$94=0,0,R68/$R$94) | T68: 0 | U68: -0.026489999 | V68: not selected
A69: DJ30 | B69: 2023-01-20 | C69: DIA | D69: CAT | E69: CAT | F69: - | G69: 237.37811 | H69: =P38 | I69: =Q38 | J69: =I69*G69 | K69: =IF($J$94=0,0,J69/$J$94) | L69: REJECTED | M69: 0 | N69: =M69*$J$94-J69 | O69: =IF(G69=0,0,N69/G69) | P69: =IF(M69>0,D69,"") | Q69: =I69+O69 | R69: =Q69*G69 | S69: =IF($R$94=0,0,R69/$R$94) | T69: 0 | U69: -0.026489999 | V69: not selected
A70: DJ30 | B70: 2023-01-20 | C70: DIA | D70: CRM | E70: CRM | F70: - | G70: 148.6778 | H70: =P39 | I70: =Q39 | J70: =I70*G70 | K70: =IF($J$94=0,0,J70/$J$94) | L70: REJECTED | M70: 0 | N70: =M70*$J$94-J70 | O70: =IF(G70=0,0,N70/G70) | P70: =IF(M70>0,D70,"") | Q70: =I70+O70 | R70: =Q70*G70 | S70: =IF($R$94=0,0,R70/$R$94) | T70: 0 | U70: -0.026489999 | V70: not selected
A71: DJ30 | B71: 2023-01-20 | C71: DIA | D71: CSCO | E71: CSCO | F71: - | G71: 42.733696 | H71: =P40 | I71: =Q40 | J71: =I71*G71 | K71: =IF($J$94=0,0,J71/$J$94) | L71: REJECTED | M71: 0 | N71: =M71*$J$94-J71 | O71: =IF(G71=0,0,N71/G71) | P71: =IF(M71>0,D71,"") | Q71: =I71+O71 | R71: =Q71*G71 | S71: =IF($R$94=0,0,R71/$R$94) | T71: 0 | U71: -0.026489999 | V71: not selected
A72: DJ30 | B72: 2023-01-20 | C72: DIA | D72: CVX | E72: CVX | F72: - | G72: 156.50061 | H72: =P41 | I72: =Q41 | J72: =I72*G72 | K72: =IF($J$94=0,0,J72/$J$94) | L72: REJECTED | M72: 0 | N72: =M72*$J$94-J72 | O72: =IF(G72=0,0,N72/G72) | P72: =IF(M72>0,D72,"") | Q72: =I72+O72 | R72: =Q72*G72 | S72: =IF($R$94=0,0,R72/$R$94) | T72: 0 | U72: -0.026489999 | V72: not selected
A73: DJ30 | B73: 2023-01-20 | C73: DIA | D73: DIS | E73: DIS | F73: - | G73: 101.09918 | H73: =P42 | I73: =Q42 | J73: =I73*G73 | K73: =IF($J$94=0,0,J73/$J$94) | L73: REJECTED | M73: 0 | N73: =M73*$J$94-J73 | O73: =IF(G73=0,0,N73/G73) | P73: =IF(M73>0,D73,"") | Q73: =I73+O73 | R73: =Q73*G73 | S73: =IF($R$94=0,0,R73/$R$94) | T73: 0 | U73: -0.026489999 | V73: not selected
A74: DJ30 | B74: 2023-01-20 | C74: DIA | D74: GS | E74: GS | F74: - | G74: 313.98856 | H74: =P43 | I74: =Q43 | J74: =I74*G74 | K74: =IF($J$94=0,0,J74/$J$94) | L74: REJECTED | M74: 0 | N74: =M74*$J$94-J74 | O74: =IF(G74=0,0,N74/G74) | P74: =IF(M74>0,D74,"") | Q74: =I74+O74 | R74: =Q74*G74 | S74: =IF($R$94=0,0,R74/$R$94) | T74: 0 | U74: -0.026489999 | V74: not selected
A75: DJ30 | B75: 2023-01-20 | C75: DIA | D75: HD | E75: HD | F75: - | G75: 287.77127 | H75: =P44 | I75: =Q44 | J75: =I75*G75 | K75: =IF($J$94=0,0,J75/$J$94) | L75: REJECTED | M75: 0 | N75: =M75*$J$94-J75 | O75: =IF(G75=0,0,N75/G75) | P75: =IF(M75>0,D75,"") | Q75: =I75+O75 | R75: =Q75*G75 | S75: =IF($R$94=0,0,R75/$R$94) | T75: 0 | U75: -0.026489999 | V75: not selected
... A93: DJ30 | B93: 2023-01-20 | C93: DIA | D93: WMT | E93: WMT | F93: - | G93: 44.985672 | H93: =P62 | I93: =Q62 | J93: =I93*G93 | K93: =IF($J$94=0,0,J93/$J$94) | L93: REJECTED | M93: 0 | N93: =M93*$J$94-J93 | O93: =IF(G93=0,0,N93/G93) | P93: =IF(M93>0,D93,"") | Q93: =I93+O93 | R93: =Q93*G93 | S93: =IF($R$94=0,0,R93/$R$94) | T93: 0 | U93: -0.026489999 | V93: not selected
A94: DJ30 | B94: 2023-01-20 | C94: DIA | D94: Tot Portfolio | J94: =SUM(J64:J93) | K94: =SUM(K64:K93) | L94: TOTAL | M94: =SUM(M64:M93) | N94: =SUM(N64:N93) | O94: =SUM(O64:O93) | R94: =SUM(R64:R93) | S94: =SUM(S64:S93) | T94: 0 | U94: -0.026489999
A95: DJ30 | B95: 2023-01-27 | C95: DIA | D95: AAPL | E95: AAPL | F95: - | G95: 143.4946 | H95: =P64 | I95: =Q64 | J95: =I95*G95 | K95: =IF($J$125=0,0,J95/$J$125) | L95: REJECTED | M95: 0 | N95: =M95*$J$125-J95 | O95: =IF(G95=0,0,N95/G95) | P95: =IF(M95>0,D95,"") | Q95: =I95+O95 | R95: =Q95*G95 | S95: =IF($R$125=0,0,R95/$R$125) | T95: 0 | U95: 0.017801471 | V95: not selected
A96: DJ30 | B96: 2023-01-27 | C96: DIA | D96: AMGN | E96: AMGN | F96: - | G96: 227.15991 | H96: =P65 | I96: =Q65 | J96: =I96*G96 | K96: =IF($J$125=0,0,J96/$J$125) | L96: REJECTED | M96: 0 | N96: =M96*$J$125-J96 | O96: =IF(G96=0,0,N96/G96) | P96: =IF(M96>0,D96,"") | Q96: =I96+O96 | R96: =Q96*G96 | S96: =IF($R$125=0,0,R96/$R$125) | T96: 0 | U96: 0.017801471 | V96: not selected
A97: DJ30 | B97: 2023-01-27 | C97: DIA | D97: AMZN | E97: AMZN | F97: - | G97: 102.24 | H97: =P66 | I97: =Q66 | J97: =I97*G97 | K97: =IF($J$125=0,0,J97/$J$125) | L97: REJECTED | M97: 0 | N97: =M97*$J$125-J97 | O97: =IF(G97=0,0,N97/G97) | P97: =IF(M97>0,D97,"") | Q97: =I97+O97 | R97: =Q97*G97 | S97: =IF($R$125=0,0,R97/$R$125) | T97: 0 | U97: 0.017801471 | V97: not selected
A98: DJ30 | B98: 2023-01-27 | C98: DIA | D98: AXP | E98: AXP | F98: - | G98: 165.68375 | H98: =P67 | I98: =Q67 | J98: =I98*G98 | K98: =IF($J$125=0,0,J98/$J$125) | L98: REJECTED | M98: 0 | N98: =M98*$J$125-J98 | O98: =IF(G98=0,0,N98/G98) | P98: =IF(M98>0,D98,"") | Q98: =I98+O98 | R98: =Q98*G98 | S98: =IF($R$125=0,0,R98/$R$125) | T98: 0 | U98: 0.017801471 | V98: not selected
A99: DJ30 | B99: 2023-01-27 | C99: DIA | D99: BA | E99: BA | F99: - | G99: 211.17 | H99: =P68 | I99: =Q68 | J99: =I99*G99 | K99: =IF($J$125=0,0,J99/$J$125) | L99: REJECTED | M99: 0 | N99: =M99*$J$125-J99 | O99: =IF(G99=0,0,N99/G99) | P99: =IF(M99>0,D99,"") | Q99: =I99+O99 | R99: =Q99*G99 | S99: =IF($R$125=0,0,R99/$R$125) | T99: 0 | U99: 0.017801471 | V99: not selected
A100: DJ30 | B100: 2023-01-27 | C100: DIA | D100: CAT | E100: CAT | F100: - | G100: 251.47572 | H100: =P69 | I100: =Q69 | J100: =I100*G100 | K100: =IF($J$125=0,0,J100/$J$125) | L100: REJECTED | M100: 0 | N100: =M100*$J$125-J100 | O100: =IF(G100=0,0,N100/G100) | P100: =IF(M100>0,D100,"") | Q100: =I100+O100 | R100: =Q100*G100 | S100: =IF($R$125=0,0,R100/$R$125) | T100: 0 | U100: 0.017801471 | V100: not selected
A101: DJ30 | B101: 2023-01-27 | C101: DIA | D101: CRM | E101: CRM | F101: - | G101: 161.72212 | H101: =P70 | I101: =Q70 | J101: =I101*G101 | K101: =IF($J$125=0,0,J101/$J$125) | L101: REJECTED | M101: 0 | N101: =M101*$J$125-J101 | O101: =IF(G101=0,0,N101/G101) | P101: =IF(M101>0,D101,"") | Q101: =I101+O101 | R101: =Q101*G101 | S101: =IF($R$125=0,0,R101/$R$125) | T101: 0 | U101: 0.017801471 | V101: not selected
A102: DJ30 | B102: 2023-01-27 | C102: DIA | D102: CSCO | E102: CSCO | F102: - | G102: 44.314053 | H102: =P71 | I102: =Q71 | J102: =I102*G102 | K102: =IF($J$125=0,0,J102/$J$125) | L102: REJECTED | M102: 0 | N102: =M102*$J$125-J102 | O102: =IF(G102=0,0,N102/G102) | P102: =IF(M102>0,D102,"") | Q102: =I102+O102 | R102: =Q102*G102 | S102: =IF($R$125=0,0,R102/$R$125) | T102: 0 | U102: 0.017801471 | V102: not selected
A103: DJ30 | B103: 2023-01-27 | C103: DIA | D103: CVX | E103: CVX | F103: - | G103: 155.2462 | H103: =P72 | I103: =Q72 | J103: =I103*G103 | K103: =IF($J$125=0,0,J103/$J$125) | L103: REJECTED | M103: 0 | N103: =M103*$J$125-J103 | O103: =IF(G103=0,0,N103/G103) | P103: =IF(M103>0,D103,"") | Q103: =I103+O103 | R103: =Q103*G103 | S103: =IF($R$125=0,0,R103/$R$125) | T103: 0 | U103: 0.017801471 | V103: not selected
A104: DJ30 | B104: 2023-01-27 | C104: DIA | D104: DIS | E104: DIS | F104: - | G104: 107.01975 | H104: =P73 | I104: =Q73 | J104: =I104*G104 | K104: =IF($J$125=0,0,J104/$J$125) | L104: REJECTED | M104: 0 | N104: =M104*$J$125-J104 | O104: =IF(G104=0,0,N104/G104) | P104: =IF(M104>0,D104,"") | Q104: =I104+O104 | R104: =Q104*G104 | S104: =IF($R$125=0,0,R104/$R$125) | T104: 0 | U104: 0.017801471 | V104: not selected
A105: DJ30 | B105: 2023-01-27 | C105: DIA | D105: GS | E105: GS | F105: - | G105: 324.8822 | H105: =P74 | I105: =Q74 | J105: =I105*G105 | K105: =IF($J$125=0,0,J105/$J$125) | L105: REJECTED | M105: 0 | N105: =M105*$J$125-J105 | O105: =IF(G105=0,0,N105/G105) | P105: =IF(M105>0,D105,"") | Q105: =I105+O105 | R105: =Q105*G105 | S105: =IF($R$125=0,0,R105/$R$125) | T105: 0 | U105: 0.017801471 | V105: not selected
A106: DJ30 | B106: 2023-01-27 | C106: DIA | D106: HD | E106: HD | F106: - | G106: 289.31509 | H106: =P75 | I106: =Q75 | J106: =I106*G106 | K106: =IF($J$125=0,0,J106/$J$125) | L106: REJECTED | M106: 0 | N106: =M106*$J$125-J106 | O106: =IF(G106=0,0,N106/G106) | P106: =IF(M106>0,D106,"") | Q106: =I106+O106 | R106: =Q106*G106 | S106: =IF($R$125=0,0,R106/$R$125) | T106: 0 | U106: 0.017801471 | V106: not selected
... A124: DJ30 | B124: 2023-01-27 | C124: DIA | D124: WMT | E124: WMT | F124: - | G124: 45.869122 | H124: =P93 | I124: =Q93 | J124: =I124*G124 | K124: =IF($J$125=0,0,J124/$J$125) | L124: REJECTED | M124: 0 | N124: =M124*$J$125-J124 | O124: =IF(G124=0,0,N124/G124) | P124: =IF(M124>0,D124,"") | Q124: =I124+O124 | R124: =Q124*G124 | S124: =IF($R$125=0,0,R124/$R$125) | T124: 0 | U124: 0.017801471 | V124: not selected
A125: DJ30 | B125: 2023-01-27 | C125: DIA | D125: Tot Portfolio | J125: =SUM(J95:J124) | K125: =SUM(K95:K124) | L125: TOTAL | M125: =SUM(M95:M124) | N125: =SUM(N95:N124) | O125: =SUM(O95:O124) | R125: =SUM(R95:R124) | S125: =SUM(S95:S124) | T125: 0 | U125: 0.017801471
A126: DJ30 | B126: 2023-02-03 | C126: DIA | D126: AAPL | E126: AAPL | F126: - | G126: 151.92155 | H126: =P95 | I126: =Q95 | J126: =I126*G126 | K126: =IF($J$156=0,0,J126/$J$156) | L126: REJECTED | M126: 0 | N126: =M126*$J$156-J126 | O126: =IF(G126=0,0,N126/G126) | P126: =IF(M126>0,D126,"") | Q126: =I126+O126 | R126: =Q126*G126 | S126: =IF($R$156=0,0,R126/$R$156) | T126: 0 | U126: -0.0018549393 | V126: not selected
A127: DJ30 | B127: 2023-02-03 | C127: DIA | D127: AMGN | E127: AMGN | F127: - | G127: 219.56552 | H127: =P96 | I127: =Q96 | J127: =I127*G127 | K127: =IF($J$156=0,0,J127/$J$156) | L127: REJECTED | M127: 0 | N127: =M127*$J$156-J127 | O127: =IF(G127=0,0,N127/G127) | P127: =IF(M127>0,D127,"") | Q127: =I127+O127 | R127: =Q127*G127 | S127: =IF($R$156=0,0,R127/$R$156) | T127: 0 | U127: -0.0018549393 | V127: not selected
A128: DJ30 | B128: 2023-02-03 | C128: DIA | D128: AMZN | E128: AMZN | F128: - | G128: 103.39 | H128: =P97 | I128: =Q97 | J128: =I128*G128 | K128: =IF($J$156=0,0,J128/$J$156) | L128: REJECTED | M128: 0 | N128: =M128*$J$156-J128 | O128: =IF(G128=0,0,N128/G128) | P128: =IF(M128>0,D128,"") | Q128: =I128+O128 | R128: =Q128*G128 | S128: =IF($R$156=0,0,R128/$R$156) | T128: 0 | U128: -0.0018549393 | V128: not selected
A129: DJ30 | B129: 2023-02-03 | C129: DIA | D129: AXP | E129: AXP | F129: - | G129: 171.98184 | H129: =P98 | I129: =Q98 | J129: =I129*G129 | K129: =IF($J$156=0,0,J129/$J$156) | L129: REJECTED | M129: 0 | N129: =M129*$J$156-J129 | O129: =IF(G129=0,0,N129/G129) | P129: =IF(M129>0,D129,"") | Q129: =I129+O129 | R129: =Q129*G129 | S129: =IF($R$156=0,0,R129/$R$156) | T129: 0 | U129: -0.0018549393 | V129: not selected
A130: DJ30 | B130: 2023-02-03 | C130: DIA | D130: BA | E130: BA | F130: - | G130: 206.00999 | H130: =P99 | I130: =Q99 | J130: =I130*G130 | K130: =IF($J$156=0,0,J130/$J$156) | L130: REJECTED | M130: 0 | N130: =M130*$J$156-J130 | O130: =IF(G130=0,0,N130/G130) | P130: =IF(M130>0,D130,"") | Q130: =I130+O130 | R130: =Q130*G130 | S130: =IF($R$156=0,0,R130/$R$156) | T130: 0 | U130: -0.0018549393 | V130: not selected
A131: DJ30 | B131: 2023-02-03 | C131: DIA | D131: CAT | E131: CAT | F131: - | G131: 235.5244 | H131: =P100 | I131: =Q100 | J131: =I131*G131 | K131: =IF($J$156=0,0,J131/$J$156) | L131: REJECTED | M131: 0 | N131: =M131*$J$156-J131 | O131: =IF(G131=0,0,N131/G131) | P131: =IF(M131>0,D131,"") | Q131: =I131+O131 | R131: =Q131*G131 | S131: =IF($R$156=0,0,R131/$R$156) | T131: 0 | U131: -0.0018549393 | V131: not selected
A132: DJ30 | B132: 2023-02-03 | C132: DIA | D132: CRM | E132: CRM | F132: - | G132: 168.13123 | H132: =P101 | I132: =Q101 | J132: =I132*G132 | K132: =IF($J$156=0,0,J132/$J$156) | L132: REJECTED | M132: 0 | N132: =M132*$J$156-J132 | O132: =IF(G132=0,0,N132/G132) | P132: =IF(M132>0,D132,"") | Q132: =I132+O132 | R132: =Q132*G132 | S132: =IF($R$156=0,0,R132/$R$156) | T132: 0 | U132: -0.0018549393 | V132: not selected
A133: DJ30 | B133: 2023-02-03 | C133: DIA | D133: CSCO | E133: CSCO | F133: - | G133: 44.423672 | H133: =P102 | I133: =Q102 | J133: =I133*G133 | K133: =IF($J$156=0,0,J133/$J$156) | L133: REJECTED | M133: 0 | N133: =M133*$J$156-J133 | O133: =IF(G133=0,0,N133/G133) | P133: =IF(M133>0,D133,"") | Q133: =I133+O133 | R133: =Q133*G133 | S133: =IF($R$156=0,0,R133/$R$156) | T133: 0 | U133: -0.0018549393 | V133: not selected
A134: DJ30 | B134: 2023-02-03 | C134: DIA | D134: CVX | E134: CVX | F134: - | G134: 146.59494 | H134: =P103 | I134: =Q103 | J134: =I134*G134 | K134: =IF($J$156=0,0,J134/$J$156) | L134: REJECTED | M134: 0 | N134: =M134*$J$156-J134 | O134: =IF(G134=0,0,N134/G134) | P134: =IF(M134>0,D134,"") | Q134: =I134+O134 | R134: =Q134*G134 | S134: =IF($R$156=0,0,R134/$R$156) | T134: 0 | U134: -0.0018549393 | V134: not selected
A135: DJ30 | B135: 2023-02-03 | C135: DIA | D135: DIS | E135: DIS | F135: - | G135: 108.16283 | H135: =P104 | I135: =Q104 | J135: =I135*G135 | K135: =IF($J$156=0,0,J135/$J$156) | L135: REJECTED | M135: 0 | N135: =M135*$J$156-J135 | O135: =IF(G135=0,0,N135/G135) | P135: =IF(M135>0,D135,"") | Q135: =I135+O135 | R135: =Q135*G135 | S135: =IF($R$156=0,0,R135/$R$156) | T135: 0 | U135: -0.0018549393 | V135: not selected
A136: DJ30 | B136: 2023-02-03 | C136: DIA | D136: GS | E136: GS | F136: - | G136: 339.80829 | H136: =P105 | I136: =Q105 | J136: =I136*G136 | K136: =IF($J$156=0,0,J136/$J$156) | L136: REJECTED | M136: 0 | N136: =M136*$J$156-J136 | O136: =IF(G136=0,0,N136/G136) | P136: =IF(M136>0,D136,"") | Q136: =I136+O136 | R136: =Q136*G136 | S136: =IF($R$156=0,0,R136/$R$156) | T136: 0 | U136: -0.0018549393 | V136: not selected
A137: DJ30 | B137: 2023-02-03 | C137: DIA | D137: HD | E137: HD | F137: - | G137: 302.84497 | H137: =P106 | I137: =Q106 | J137: =I137*G137 | K137: =IF($J$156=0,0,J137/$J$156) | L137: REJECTED | M137: 0 | N137: =M137*$J$156-J137 | O137: =IF(G137=0,0,N137/G137) | P137: =IF(M137>0,D137,"") | Q137: =I137+O137 | R137: =Q137*G137 | S137: =IF($R$156=0,0,R137/$R$156) | T137: 0 | U137: -0.0018549393 | V137: not selected
... A155: DJ30 | B155: 2023-02-03 | C155: DIA | D155: WMT | E155: WMT | F155: - | G155: 45.36018 | H155: =P124 | I155: =Q124 | J155: =I155*G155 | K155: =IF($J$156=0,0,J155/$J$156) | L155: REJECTED | M155: 0 | N155: =M155*$J$156-J155 | O155: =IF(G155=0,0,N155/G155) | P155: =IF(M155>0,D155,"") | Q155: =I155+O155 | R155: =Q155*G155 | S155: =IF($R$156=0,0,R155/$R$156) | T155: 0 | U155: -0.0018549393 | V155: not selected
A156: DJ30 | B156: 2023-02-03 | C156: DIA | D156: Tot Portfolio | J156: =SUM(J126:J155) | K156: =SUM(K126:K155) | L156: TOTAL | M156: =SUM(M126:M155) | N156: =SUM(N126:N155) | O156: =SUM(O126:O155) | R156: =SUM(R126:R155) | S156: =SUM(S126:S155) | T156: 0 | U156: -0.0018549393
A157: DJ30 | B157: 2023-02-10 | C157: DIA | D157: AAPL | E157: AAPL | F157: - | G157: 148.71654 | H157: =P126 | I157: =Q126 | J157: =I157*G157 | K157: =IF($J$187=0,0,J157/$J$187) | L157: REJECTED | M157: 0 | N157: =M157*$J$187-J157 | O157: =IF(G157=0,0,N157/G157) | P157: =IF(M157>0,D157,"") | Q157: =I157+O157 | R157: =Q157*G157 | S157: =IF($R$187=0,0,R157/$R$187) | T157: 0 | U157: -0.00073737765 | V157: not selected
A158: DJ30 | B158: 2023-02-10 | C158: DIA | D158: AMGN | E158: AMGN | F158: - | G158: 217.17438 | H158: =P127 | I158: =Q127 | J158: =I158*G158 | K158: =IF($J$187=0,0,J158/$J$187) | L158: REJECTED | M158: 0 | N158: =M158*$J$187-J158 | O158: =IF(G158=0,0,N158/G158) | P158: =IF(M158>0,D158,"") | Q158: =I158+O158 | R158: =Q158*G158 | S158: =IF($R$187=0,0,R158/$R$187) | T158: 0 | U158: -0.00073737765 | V158: not selected
A159: DJ30 | B159: 2023-02-10 | C159: DIA | D159: AMZN | E159: AMZN | F159: - | G159: 97.610001 | H159: =P128 | I159: =Q128 | J159: =I159*G159 | K159: =IF($J$187=0,0,J159/$J$187) | L159: REJECTED | M159: 0 | N159: =M159*$J$187-J159 | O159: =IF(G159=0,0,N159/G159) | P159: =IF(M159>0,D159,"") | Q159: =I159+O159 | R159: =Q159*G159 | S159: =IF($R$187=0,0,R159/$R$187) | T159: 0 | U159: -0.00073737765 | V159: not selected
A160: DJ30 | B160: 2023-02-10 | C160: DIA | D160: AXP | E160: AXP | F160: - | G160: 172.35686 | H160: =P129 | I160: =Q129 | J160: =I160*G160 | K160: =IF($J$187=0,0,J160/$J$187) | L160: REJECTED | M160: 0 | N160: =M160*$J$187-J160 | O160: =IF(G160=0,0,N160/G160) | P160: =IF(M160>0,D160,"") | Q160: =I160+O160 | R160: =Q160*G160 | S160: =IF($R$187=0,0,R160/$R$187) | T160: 0 | U160: -0.00073737765 | V160: not selected
A161: DJ30 | B161: 2023-02-10 | C161: DIA | D161: BA | E161: BA | F161: - | G161: 212.89 | H161: =P130 | I161: =Q130 | J161: =I161*G161 | K161: =IF($J$187=0,0,J161/$J$187) | L161: REJECTED | M161: 0 | N161: =M161*$J$187-J161 | O161: =IF(G161=0,0,N161/G161) | P161: =IF(M161>0,D161,"") | Q161: =I161+O161 | R161: =Q161*G161 | S161: =IF($R$187=0,0,R161/$R$187) | T161: 0 | U161: -0.00073737765 | V161: not selected
A162: DJ30 | B162: 2023-02-10 | C162: DIA | D162: CAT | E162: CAT | F162: - | G162: 235.43884 | H162: =P131 | I162: =Q131 | J162: =I162*G162 | K162: =IF($J$187=0,0,J162/$J$187) | L162: REJECTED | M162: 0 | N162: =M162*$J$187-J162 | O162: =IF(G162=0,0,N162/G162) | P162: =IF(M162>0,D162,"") | Q162: =I162+O162 | R162: =Q162*G162 | S162: =IF($R$187=0,0,R162/$R$187) | T162: 0 | U162: -0.00073737765 | V162: not selected
A163: DJ30 | B163: 2023-02-10 | C163: DIA | D163: CRM | E163: CRM | F163: - | G163: 164.18944 | H163: =P132 | I163: =Q132 | J163: =I163*G163 | K163: =IF($J$187=0,0,J163/$J$187) | L163: REJECTED | M163: 0 | N163: =M163*$J$187-J163 | O163: =IF(G163=0,0,N163/G163) | P163: =IF(M163>0,D163,"") | Q163: =I163+O163 | R163: =Q163*G163 | S163: =IF($R$187=0,0,R163/$R$187) | T163: 0 | U163: -0.00073737765 | V163: not selected
A164: DJ30 | B164: 2023-02-10 | C164: DIA | D164: CSCO | E164: CSCO | F164: - | G164: 43.172176 | H164: =P133 | I164: =Q133 | J164: =I164*G164 | K164: =IF($J$187=0,0,J164/$J$187) | L164: REJECTED | M164: 0 | N164: =M164*$J$187-J164 | O164: =IF(G164=0,0,N164/G164) | P164: =IF(M164>0,D164,"") | Q164: =I164+O164 | R164: =Q164*G164 | S164: =IF($R$187=0,0,R164/$R$187) | T164: 0 | U164: -0.00073737765 | V164: not selected
A165: DJ30 | B165: 2023-02-10 | C165: DIA | D165: CVX | E165: CVX | F165: - | G165: 148.77505 | H165: =P134 | I165: =Q134 | J165: =I165*G165 | K165: =IF($J$187=0,0,J165/$J$187) | L165: REJECTED | M165: 0 | N165: =M165*$J$187-J165 | O165: =IF(G165=0,0,N165/G165) | P165: =IF(M165>0,D165,"") | Q165: =I165+O165 | R165: =Q165*G165 | S165: =IF($R$187=0,0,R165/$R$187) | T165: 0 | U165: -0.00073737765 | V165: not selected
A166: DJ30 | B166: 2023-02-10 | C166: DIA | D166: DIS | E166: DIS | F166: - | G166: 105.57379 | H166: =P135 | I166: =Q135 | J166: =I166*G166 | K166: =IF($J$187=0,0,J166/$J$187) | L166: REJECTED | M166: 0 | N166: =M166*$J$187-J166 | O166: =IF(G166=0,0,N166/G166) | P166: =IF(M166>0,D166,"") | Q166: =I166+O166 | R166: =Q166*G166 | S166: =IF($R$187=0,0,R166/$R$187) | T166: 0 | U166: -0.00073737765 | V166: not selected
A167: DJ30 | B167: 2023-02-10 | C167: DIA | D167: GS | E167: GS | F167: - | G167: 341.02985 | H167: =P136 | I167: =Q136 | J167: =I167*G167 | K167: =IF($J$187=0,0,J167/$J$187) | L167: REJECTED | M167: 0 | N167: =M167*$J$187-J167 | O167: =IF(G167=0,0,N167/G167) | P167: =IF(M167>0,D167,"") | Q167: =I167+O167 | R167: =Q167*G167 | S167: =IF($R$187=0,0,R167/$R$187) | T167: 0 | U167: -0.00073737765 | V167: not selected
A168: DJ30 | B168: 2023-02-10 | C168: DIA | D168: HD | E168: HD | F168: - | G168: 289.17813 | H168: =P137 | I168: =Q137 | J168: =I168*G168 | K168: =IF($J$187=0,0,J168/$J$187) | L168: REJECTED | M168: 0 | N168: =M168*$J$187-J168 | O168: =IF(G168=0,0,N168/G168) | P168: =IF(M168>0,D168,"") | Q168: =I168+O168 | R168: =Q168*G168 | S168: =IF($R$187=0,0,R168/$R$187) | T168: 0 | U168: -0.00073737765 | V168: not selected
... A186: DJ30 | B186: 2023-02-10 | C186: DIA | D186: WMT | E186: WMT | F186: - | G186: 46.003559 | H186: =P155 | I186: =Q155 | J186: =I186*G186 | K186: =IF($J$187=0,0,J186/$J$187) | L186: REJECTED | M186: 0 | N186: =M186*$J$187-J186 | O186: =IF(G186=0,0,N186/G186) | P186: =IF(M186>0,D186,"") | Q186: =I186+O186 | R186: =Q186*G186 | S186: =IF($R$187=0,0,R186/$R$187) | T186: 0 | U186: -0.00073737765 | V186: not selected
A187: DJ30 | B187: 2023-02-10 | C187: DIA | D187: Tot Portfolio | J187: =SUM(J157:J186) | K187: =SUM(K157:K186) | L187: TOTAL | M187: =SUM(M157:M186) | N187: =SUM(N157:N186) | O187: =SUM(O157:O186) | R187: =SUM(R157:R186) | S187: =SUM(S157:S186) | T187: 0 | U187: -0.00073737765
A188: DJ30 | B188: 2023-02-17 | C188: DIA | D188: AAPL | E188: AAPL | F188: - | G188: 150.23314 | H188: =P157 | I188: =Q157 | J188: =I188*G188 | K188: =IF($J$218=0,0,J188/$J$218) | L188: REJECTED | M188: 0 | N188: =M188*$J$218-J188 | O188: =IF(G188=0,0,N188/G188) | P188: =IF(M188>0,D188,"") | Q188: =I188+O188 | R188: =Q188*G188 | S188: =IF($R$218=0,0,R188/$R$218) | T188: 0 | U188: 0.00033766872 | V188: not selected
A189: DJ30 | B189: 2023-02-17 | C189: DIA | D189: AMGN | E189: AMGN | F189: - | G189: 217.30978 | H189: =P158 | I189: =Q158 | J189: =I189*G189 | K189: =IF($J$218=0,0,J189/$J$218) | L189: REJECTED | M189: 0 | N189: =M189*$J$218-J189 | O189: =IF(G189=0,0,N189/G189) | P189: =IF(M189>0,D189,"") | Q189: =I189+O189 | R189: =Q189*G189 | S189: =IF($R$218=0,0,R189/$R$218) | T189: 0 | U189: 0.00033766872 | V189: not selected
A190: DJ30 | B190: 2023-02-17 | C190: DIA | D190: AMZN | E190: AMZN | F190: - | G190: 97.199997 | H190: =P159 | I190: =Q159 | J190: =I190*G190 | K190: =IF($J$218=0,0,J190/$J$218) | L190: REJECTED | M190: 0 | N190: =M190*$J$218-J190 | O190: =IF(G190=0,0,N190/G190) | P190: =IF(M190>0,D190,"") | Q190: =I190+O190 | R190: =Q190*G190 | S190: =IF($R$218=0,0,R190/$R$218) | T190: 0 | U190: 0.00033766872 | V190: not selected
A191: DJ30 | B191: 2023-02-17 | C191: DIA | D191: AXP | E191: AXP | F191: - | G191: 170.48187 | H191: =P160 | I191: =Q160 | J191: =I191*G191 | K191: =IF($J$218=0,0,J191/$J$218) | L191: REJECTED | M191: 0 | N191: =M191*$J$218-J191 | O191: =IF(G191=0,0,N191/G191) | P191: =IF(M191>0,D191,"") | Q191: =I191+O191 | R191: =Q191*G191 | S191: =IF($R$218=0,0,R191/$R$218) | T191: 0 | U191: 0.00033766872 | V191: not selected
A192: DJ30 | B192: 2023-02-17 | C192: DIA | D192: BA | E192: BA | F192: - | G192: 211.66 | H192: =P161 | I192: =Q161 | J192: =I192*G192 | K192: =IF($J$218=0,0,J192/$J$218) | L192: REJECTED | M192: 0 | N192: =M192*$J$218-J192 | O192: =IF(G192=0,0,N192/G192) | P192: =IF(M192>0,D192,"") | Q192: =I192+O192 | R192: =Q192*G192 | S192: =IF($R$218=0,0,R192/$R$218) | T192: 0 | U192: 0.00033766872 | V192: not selected
A193: DJ30 | B193: 2023-02-17 | C193: DIA | D193: CAT | E193: CAT | F193: - | G193: 235.55292 | H193: =P162 | I193: =Q162 | J193: =I193*G193 | K193: =IF($J$218=0,0,J193/$J$218) | L193: REJECTED | M193: 0 | N193: =M193*$J$218-J193 | O193: =IF(G193=0,0,N193/G193) | P193: =IF(M193>0,D193,"") | Q193: =I193+O193 | R193: =Q193*G193 | S193: =IF($R$218=0,0,R193/$R$218) | T193: 0 | U193: 0.00033766872 | V193: not selected
A194: DJ30 | B194: 2023-02-17 | C194: DIA | D194: CRM | E194: CRM | F194: - | G194: 162.36104 | H194: =P163 | I194: =Q163 | J194: =I194*G194 | K194: =IF($J$218=0,0,J194/$J$218) | L194: REJECTED | M194: 0 | N194: =M194*$J$218-J194 | O194: =IF(G194=0,0,N194/G194) | P194: =IF(M194>0,D194,"") | Q194: =I194+O194 | R194: =Q194*G194 | S194: =IF($R$218=0,0,R194/$R$218) | T194: 0 | U194: 0.00033766872 | V194: not selected
A195: DJ30 | B195: 2023-02-17 | C195: DIA | D195: CSCO | E195: CSCO | F195: - | G195: 46.378567 | H195: =P164 | I195: =Q164 | J195: =I195*G195 | K195: =IF($J$218=0,0,J195/$J$218) | L195: REJECTED | M195: 0 | N195: =M195*$J$218-J195 | O195: =IF(G195=0,0,N195/G195) | P195: =IF(M195>0,D195,"") | Q195: =I195+O195 | R195: =Q195*G195 | S195: =IF($R$218=0,0,R195/$R$218) | T195: 0 | U195: 0.00033766872 | V195: not selected
A196: DJ30 | B196: 2023-02-17 | C196: DIA | D196: CVX | E196: CVX | F196: - | G196: 142.13062 | H196: =P165 | I196: =Q165 | J196: =I196*G196 | K196: =IF($J$218=0,0,J196/$J$218) | L196: REJECTED | M196: 0 | N196: =M196*$J$218-J196 | O196: =IF(G196=0,0,N196/G196) | P196: =IF(M196>0,D196,"") | Q196: =I196+O196 | R196: =Q196*G196 | S196: =IF($R$218=0,0,R196/$R$218) | T196: 0 | U196: 0.00033766872 | V196: not selected
A197: DJ30 | B197: 2023-02-17 | C197: DIA | D197: DIS | E197: DIS | F197: - | G197: 102.79915 | H197: =P166 | I197: =Q166 | J197: =I197*G197 | K197: =IF($J$218=0,0,J197/$J$218) | L197: REJECTED | M197: 0 | N197: =M197*$J$218-J197 | O197: =IF(G197=0,0,N197/G197) | P197: =IF(M197>0,D197,"") | Q197: =I197+O197 | R197: =Q197*G197 | S197: =IF($R$218=0,0,R197/$R$218) | T197: 0 | U197: 0.00033766872 | V197: not selected
A198: DJ30 | B198: 2023-02-17 | C198: DIA | D198: GS | E198: GS | F198: - | G198: 338.47644 | H198: =P167 | I198: =Q167 | J198: =I198*G198 | K198: =IF($J$218=0,0,J198/$J$218) | L198: REJECTED | M198: 0 | N198: =M198*$J$218-J198 | O198: =IF(G198=0,0,N198/G198) | P198: =IF(M198>0,D198,"") | Q198: =I198+O198 | R198: =Q198*G198 | S198: =IF($R$218=0,0,R198/$R$218) | T198: 0 | U198: 0.00033766872 | V198: not selected
A199: DJ30 | B199: 2023-02-17 | C199: DIA | D199: HD | E199: HD | F199: - | G199: 290.46628 | H199: =P168 | I199: =Q168 | J199: =I199*G199 | K199: =IF($J$218=0,0,J199/$J$218) | L199: REJECTED | M199: 0 | N199: =M199*$J$218-J199 | O199: =IF(G199=0,0,N199/G199) | P199: =IF(M199>0,D199,"") | Q199: =I199+O199 | R199: =Q199*G199 | S199: =IF($R$218=0,0,R199/$R$218) | T199: 0 | U199: 0.00033766872 | V199: not selected
... A217: DJ30 | B217: 2023-02-17 | C217: DIA | D217: WMT | E217: WMT | F217: - | G217: 46.87421 | H217: =P186 | I217: =Q186 | J217: =I217*G217 | K217: =IF($J$218=0,0,J217/$J$218) | L217: REJECTED | M217: 0 | N217: =M217*$J$218-J217 | O217: =IF(G217=0,0,N217/G217) | P217: =IF(M217>0,D217,"") | Q217: =I217+O217 | R217: =Q217*G217 | S217: =IF($R$218=0,0,R217/$R$218) | T217: 0 | U217: 0.00033766872 | V217: not selected
A218: DJ30 | B218: 2023-02-17 | C218: DIA | D218: Tot Portfolio | J218: =SUM(J188:J217) | K218: =SUM(K188:K217) | L218: TOTAL | M218: =SUM(M188:M217) | N218: =SUM(N188:N217) | O218: =SUM(O188:O217) | R218: =SUM(R188:R217) | S218: =SUM(S188:S217) | T218: 0 | U218: 0.00033766872
A219: DJ30 | B219: 2023-02-24 | C219: DIA | D219: AAPL | E219: AAPL | F219: - | G219: 144.48184 | H219: =P188 | I219: =Q188 | J219: =I219*G219 | K219: =IF($J$249=0,0,J219/$J$249) | L219: REJECTED | M219: 0 | N219: =M219*$J$249-J219 | O219: =IF(G219=0,0,N219/G219) | P219: =IF(M219>0,D219,"") | Q219: =I219+O219 | R219: =Q219*G219 | S219: =IF($R$249=0,0,R219/$R$249) | T219: 0 | U219: -0.030062717 | V219: not selected
...

Sheet Holdings_By_Week
A1: Market | B1: WeekEnding | C1: Benchmark | D1: Asset | E1: Company | F1: Sector | G1: last_price | H1: qty_after | I1: value_after | J1: weight_after
A2: DJ30 | B2: 2024-01-05 | C2: DIA | D2: NVDA | E2: NVDA | F2: - | G2: =Rebalance_Audit!G1636 | H2: =Rebalance_Audit!Q1636 | I2: =Rebalance_Audit!R1636 | J2: =Rebalance_Audit!S1636
A3: DJ30 | B3: 2024-01-05 | C3: DIA | D3: AMZN | E3: AMZN | F3: - | G3: =Rebalance_Audit!G1616 | H3: =Rebalance_Audit!Q1616 | I3: =Rebalance_Audit!R1616 | J3: =Rebalance_Audit!S1616
A4: DJ30 | B4: 2024-01-05 | C4: DIA | D4: CRM | E4: CRM | F4: - | G4: =Rebalance_Audit!G1620 | H4: =Rebalance_Audit!Q1620 | I4: =Rebalance_Audit!R1620 | J4: =Rebalance_Audit!S1620
A5: DJ30 | B5: 2024-01-05 | C5: DIA | D5: IBM | E5: IBM | F5: - | G5: =Rebalance_Audit!G1627 | H5: =Rebalance_Audit!Q1627 | I5: =Rebalance_Audit!R1627 | J5: =Rebalance_Audit!S1627
A6: DJ30 | B6: 2024-01-05 | C6: DIA | D6: JPM | E6: JPM | F6: - | G6: =Rebalance_Audit!G1629 | H6: =Rebalance_Audit!Q1629 | I6: =Rebalance_Audit!R1629 | J6: =Rebalance_Audit!S1629
A7: DJ30 | B7: 2024-01-12 | C7: DIA | D7: NVDA | E7: NVDA | F7: - | G7: =Rebalance_Audit!G1667 | H7: =Rebalance_Audit!Q1667 | I7: =Rebalance_Audit!R1667 | J7: =Rebalance_Audit!S1667
A8: DJ30 | B8: 2024-01-12 | C8: DIA | D8: AMZN | E8: AMZN | F8: - | G8: =Rebalance_Audit!G1647 | H8: =Rebalance_Audit!Q1647 | I8: =Rebalance_Audit!R1647 | J8: =Rebalance_Audit!S1647
A9: DJ30 | B9: 2024-01-12 | C9: DIA | D9: CRM | E9: CRM | F9: - | G9: =Rebalance_Audit!G1651 | H9: =Rebalance_Audit!Q1651 | I9: =Rebalance_Audit!R1651 | J9: =Rebalance_Audit!S1651
A10: DJ30 | B10: 2024-01-12 | C10: DIA | D10: AMGN | E10: AMGN | F10: - | G10: =Rebalance_Audit!G1646 | H10: =Rebalance_Audit!Q1646 | I10: =Rebalance_Audit!R1646 | J10: =Rebalance_Audit!S1646
A11: DJ30 | B11: 2024-01-12 | C11: DIA | D11: JPM | E11: JPM | F11: - | G11: =Rebalance_Audit!G1660 | H11: =Rebalance_Audit!Q1660 | I11: =Rebalance_Audit!R1660 | J11: =Rebalance_Audit!S1660
A12: DJ30 | B12: 2024-01-19 | C12: DIA | D12: NVDA | E12: NVDA | F12: - | G12: =Rebalance_Audit!G1698 | H12: =Rebalance_Audit!Q1698 | I12: =Rebalance_Audit!R1698 | J12: =Rebalance_Audit!S1698
A13: DJ30 | B13: 2024-01-19 | C13: DIA | D13: AMZN | E13: AMZN | F13: - | G13: =Rebalance_Audit!G1678 | H13: =Rebalance_Audit!Q1678 | I13: =Rebalance_Audit!R1678 | J13: =Rebalance_Audit!S1678
A14: DJ30 | B14: 2024-01-19 | C14: DIA | D14: CRM | E14: CRM | F14: - | G14: =Rebalance_Audit!G1682 | H14: =Rebalance_Audit!Q1682 | I14: =Rebalance_Audit!R1682 | J14: =Rebalance_Audit!S1682
A15: DJ30 | B15: 2024-01-19 | C15: DIA | D15: AMGN | E15: AMGN | F15: - | G15: =Rebalance_Audit!G1677 | H15: =Rebalance_Audit!Q1677 | I15: =Rebalance_Audit!R1677 | J15: =Rebalance_Audit!S1677
A16: DJ30 | B16: 2024-01-19 | C16: DIA | D16: JPM | E16: JPM | F16: - | G16: =Rebalance_Audit!G1691 | H16: =Rebalance_Audit!Q1691 | I16: =Rebalance_Audit!R1691 | J16: =Rebalance_Audit!S1691
A17: DJ30 | B17: 2024-01-26 | C17: DIA | D17: NVDA | E17: NVDA | F17: - | G17: =Rebalance_Audit!G1729 | H17: =Rebalance_Audit!Q1729 | I17: =Rebalance_Audit!R1729 | J17: =Rebalance_Audit!S1729
A18: DJ30 | B18: 2024-01-26 | C18: DIA | D18: IBM | E18: IBM | F18: - | G18: =Rebalance_Audit!G1720 | H18: =Rebalance_Audit!Q1720 | I18: =Rebalance_Audit!R1720 | J18: =Rebalance_Audit!S1720
A19: DJ30 | B19: 2024-01-26 | C19: DIA | D19: CRM | E19: CRM | F19: - | G19: =Rebalance_Audit!G1713 | H19: =Rebalance_Audit!Q1713 | I19: =Rebalance_Audit!R1713 | J19: =Rebalance_Audit!S1713
A20: DJ30 | B20: 2024-01-26 | C20: DIA | D20: AMGN | E20: AMGN | F20: - | G20: =Rebalance_Audit!G1708 | H20: =Rebalance_Audit!Q1708 | I20: =Rebalance_Audit!R1708 | J20: =Rebalance_Audit!S1708
A21: DJ30 | B21: 2024-01-26 | C21: DIA | D21: JPM | E21: JPM | F21: - | G21: =Rebalance_Audit!G1722 | H21: =Rebalance_Audit!Q1722 | I21: =Rebalance_Audit!R1722 | J21: =Rebalance_Audit!S1722
A22: DJ30 | B22: 2024-02-02 | C22: DIA | D22: NVDA | E22: NVDA | F22: - | G22: =Rebalance_Audit!G1760 | H22: =Rebalance_Audit!Q1760 | I22: =Rebalance_Audit!R1760 | J22: =Rebalance_Audit!S1760
A23: DJ30 | B23: 2024-02-02 | C23: DIA | D23: IBM | E23: IBM | F23: - | G23: =Rebalance_Audit!G1751 | H23: =Rebalance_Audit!Q1751 | I23: =Rebalance_Audit!R1751 | J23: =Rebalance_Audit!S1751
A24: DJ30 | B24: 2024-02-02 | C24: DIA | D24: CRM | E24: CRM | F24: - | G24: =Rebalance_Audit!G1744 | H24: =Rebalance_Audit!Q1744 | I24: =Rebalance_Audit!R1744 | J24: =Rebalance_Audit!S1744
A25: DJ30 | B25: 2024-02-02 | C25: DIA | D25: AMGN | E25: AMGN | F25: - | G25: =Rebalance_Audit!G1739 | H25: =Rebalance_Audit!Q1739 | I25: =Rebalance_Audit!R1739 | J25: =Rebalance_Audit!S1739
A26: DJ30 | B26: 2024-02-02 | C26: DIA | D26: CAT | E26: CAT | F26: - | G26: =Rebalance_Audit!G1743 | H26: =Rebalance_Audit!Q1743 | I26: =Rebalance_Audit!R1743 | J26: =Rebalance_Audit!S1743
A27: DJ30 | B27: 2024-02-09 | C27: DIA | D27: NVDA | E27: NVDA | F27: - | G27: =Rebalance_Audit!G1791 | H27: =Rebalance_Audit!Q1791 | I27: =Rebalance_Audit!R1791 | J27: =Rebalance_Audit!S1791
A28: DJ30 | B28: 2024-02-09 | C28: DIA | D28: IBM | E28: IBM | F28: - | G28: =Rebalance_Audit!G1782 | H28: =Rebalance_Audit!Q1782 | I28: =Rebalance_Audit!R1782 | J28: =Rebalance_Audit!S1782
A29: DJ30 | B29: 2024-02-09 | C29: DIA | D29: CRM | E29: CRM | F29: - | G29: =Rebalance_Audit!G1775 | H29: =Rebalance_Audit!Q1775 | I29: =Rebalance_Audit!R1775 | J29: =Rebalance_Audit!S1775
A30: DJ30 | B30: 2024-02-09 | C30: DIA | D30: AMGN | E30: AMGN | F30: - | G30: =Rebalance_Audit!G1770 | H30: =Rebalance_Audit!Q1770 | I30: =Rebalance_Audit!R1770 | J30: =Rebalance_Audit!S1770
A31: DJ30 | B31: 2024-02-09 | C31: DIA | D31: CAT | E31: CAT | F31: - | G31: =Rebalance_Audit!G1774 | H31: =Rebalance_Audit!Q1774 | I31: =Rebalance_Audit!R1774 | J31: =Rebalance_Audit!S1774
A32: DJ30 | B32: 2024-02-16 | C32: DIA | D32: NVDA | E32: NVDA | F32: - | G32: =Rebalance_Audit!G1822 | H32: =Rebalance_Audit!Q1822 | I32: =Rebalance_Audit!R1822 | J32: =Rebalance_Audit!S1822
A33: DJ30 | B33: 2024-02-16 | C33: DIA | D33: IBM | E33: IBM | F33: - | G33: =Rebalance_Audit!G1813 | H33: =Rebalance_Audit!Q1813 | I33: =Rebalance_Audit!R1813 | J33: =Rebalance_Audit!S1813
A34: DJ30 | B34: 2024-02-16 | C34: DIA | D34: CRM | E34: CRM | F34: - | G34: =Rebalance_Audit!G1806 | H34: =Rebalance_Audit!Q1806 | I34: =Rebalance_Audit!R1806 | J34: =Rebalance_Audit!S1806
A35: DJ30 | B35: 2024-02-16 | C35: DIA | D35: AMGN | E35: AMGN | F35: - | G35: =Rebalance_Audit!G1801 | H35: =Rebalance_Audit!Q1801 | I35: =Rebalance_Audit!R1801 | J35: =Rebalance_Audit!S1801
A36: DJ30 | B36: 2024-02-16 | C36: DIA | D36: CAT | E36: CAT | F36: - | G36: =Rebalance_Audit!G1805 | H36: =Rebalance_Audit!Q1805 | I36: =Rebalance_Audit!R1805 | J36: =Rebalance_Audit!S1805
A37: DJ30 | B37: 2024-02-23 | C37: DIA | D37: NVDA | E37: NVDA | F37: - | G37: =Rebalance_Audit!G1853 | H37: =Rebalance_Audit!Q1853 | I37: =Rebalance_Audit!R1853 | J37: =Rebalance_Audit!S1853
A38: DJ30 | B38: 2024-02-23 | C38: DIA | D38: IBM | E38: IBM | F38: - | G38: =Rebalance_Audit!G1844 | H38: =Rebalance_Audit!Q1844 | I38: =Rebalance_Audit!R1844 | J38: =Rebalance_Audit!S1844
A39: DJ30 | B39: 2024-02-23 | C39: DIA | D39: CRM | E39: CRM | F39: - | G39: =Rebalance_Audit!G1837 | H39: =Rebalance_Audit!Q1837 | I39: =Rebalance_Audit!R1837 | J39: =Rebalance_Audit!S1837
A40: DJ30 | B40: 2024-02-23 | C40: DIA | D40: AMGN | E40: AMGN | F40: - | G40: =Rebalance_Audit!G1832 | H40: =Rebalance_Audit!Q1832 | I40: =Rebalance_Audit!R1832 | J40: =Rebalance_Audit!S1832
A41: DJ30 | B41: 2024-02-23 | C41: DIA | D41: CAT | E41: CAT | F41: - | G41: =Rebalance_Audit!G1836 | H41: =Rebalance_Audit!Q1836 | I41: =Rebalance_Audit!R1836 | J41: =Rebalance_Audit!S1836
A42: DJ30 | B42: 2024-03-01 | C42: DIA | D42: NVDA | E42: NVDA | F42: - | G42: =Rebalance_Audit!G1884 | H42: =Rebalance_Audit!Q1884 | I42: =Rebalance_Audit!R1884 | J42: =Rebalance_Audit!S1884
A43: DJ30 | B43: 2024-03-01 | C43: DIA | D43: IBM | E43: IBM | F43: - | G43: =Rebalance_Audit!G1875 | H43: =Rebalance_Audit!Q1875 | I43: =Rebalance_Audit!R1875 | J43: =Rebalance_Audit!S1875
A44: DJ30 | B44: 2024-03-01 | C44: DIA | D44: CAT | E44: CAT | F44: - | G44: =Rebalance_Audit!G1867 | H44: =Rebalance_Audit!Q1867 | I44: =Rebalance_Audit!R1867 | J44: =Rebalance_Audit!S1867
A45: DJ30 | B45: 2024-03-01 | C45: DIA | D45: CRM | E45: CRM | F45: - | G45: =Rebalance_Audit!G1868 | H45: =Rebalance_Audit!Q1868 | I45: =Rebalance_Audit!R1868 | J45: =Rebalance_Audit!S1868
A46: DJ30 | B46: 2024-03-01 | C46: DIA | D46: AMGN | E46: AMGN | F46: - | G46: =Rebalance_Audit!G1863 | H46: =Rebalance_Audit!Q1863 | I46: =Rebalance_Audit!R1863 | J46: =Rebalance_Audit!S1863
A47: DJ30 | B47: 2024-03-08 | C47: DIA | D47: NVDA | E47: NVDA | F47: - | G47: =Rebalance_Audit!G1915 | H47: =Rebalance_Audit!Q1915 | I47: =Rebalance_Audit!R1915 | J47: =Rebalance_Audit!S1915
A48: DJ30 | B48: 2024-03-08 | C48: DIA | D48: IBM | E48: IBM | F48: - | G48: =Rebalance_Audit!G1906 | H48: =Rebalance_Audit!Q1906 | I48: =Rebalance_Audit!R1906 | J48: =Rebalance_Audit!S1906
A49: DJ30 | B49: 2024-03-08 | C49: DIA | D49: CAT | E49: CAT | F49: - | G49: =Rebalance_Audit!G1898 | H49: =Rebalance_Audit!Q1898 | I49: =Rebalance_Audit!R1898 | J49: =Rebalance_Audit!S1898
A50: DJ30 | B50: 2024-03-08 | C50: DIA | D50: CRM | E50: CRM | F50: - | G50: =Rebalance_Audit!G1899 | H50: =Rebalance_Audit!Q1899 | I50: =Rebalance_Audit!R1899 | J50: =Rebalance_Audit!S1899
A51: DJ30 | B51: 2024-03-08 | C51: DIA | D51: AMGN | E51: AMGN | F51: - | G51: =Rebalance_Audit!G1894 | H51: =Rebalance_Audit!Q1894 | I51: =Rebalance_Audit!R1894 | J51: =Rebalance_Audit!S1894
A52: DJ30 | B52: 2024-03-15 | C52: DIA | D52: NVDA | E52: NVDA | F52: - | G52: =Rebalance_Audit!G1946 | H52: =Rebalance_Audit!Q1946 | I52: =Rebalance_Audit!R1946 | J52: =Rebalance_Audit!S1946
A53: DJ30 | B53: 2024-03-15 | C53: DIA | D53: IBM | E53: IBM | F53: - | G53: =Rebalance_Audit!G1937 | H53: =Rebalance_Audit!Q1937 | I53: =Rebalance_Audit!R1937 | J53: =Rebalance_Audit!S1937
A54: DJ30 | B54: 2024-03-15 | C54: DIA | D54: CAT | E54: CAT | F54: - | G54: =Rebalance_Audit!G1929 | H54: =Rebalance_Audit!Q1929 | I54: =Rebalance_Audit!R1929 | J54: =Rebalance_Audit!S1929
A55: DJ30 | B55: 2024-03-15 | C55: DIA | D55: CRM | E55: CRM | F55: - | G55: =Rebalance_Audit!G1930 | H55: =Rebalance_Audit!Q1930 | I55: =Rebalance_Audit!R1930 | J55: =Rebalance_Audit!S1930
A56: DJ30 | B56: 2024-03-15 | C56: DIA | D56: AMGN | E56: AMGN | F56: - | G56: =Rebalance_Audit!G1925 | H56: =Rebalance_Audit!Q1925 | I56: =Rebalance_Audit!R1925 | J56: =Rebalance_Audit!S1925
A57: DJ30 | B57: 2024-03-22 | C57: DIA | D57: NVDA | E57: NVDA | F57: - | G57: =Rebalance_Audit!G1977 | H57: =Rebalance_Audit!Q1977 | I57: =Rebalance_Audit!R1977 | J57: =Rebalance_Audit!S1977
A58: DJ30 | B58: 2024-03-22 | C58: DIA | D58: IBM | E58: IBM | F58: - | G58: =Rebalance_Audit!G1968 | H58: =Rebalance_Audit!Q1968 | I58: =Rebalance_Audit!R1968 | J58: =Rebalance_Audit!S1968
A59: DJ30 | B59: 2024-03-22 | C59: DIA | D59: CAT | E59: CAT | F59: - | G59: =Rebalance_Audit!G1960 | H59: =Rebalance_Audit!Q1960 | I59: =Rebalance_Audit!R1960 | J59: =Rebalance_Audit!S1960
A60: DJ30 | B60: 2024-03-22 | C60: DIA | D60: CRM | E60: CRM | F60: - | G60: =Rebalance_Audit!G1961 | H60: =Rebalance_Audit!Q1961 | I60: =Rebalance_Audit!R1961 | J60: =Rebalance_Audit!S1961
A61: DJ30 | B61: 2024-03-22 | C61: DIA | D61: AMGN | E61: AMGN | F61: - | G61: =Rebalance_Audit!G1956 | H61: =Rebalance_Audit!Q1956 | I61: =Rebalance_Audit!R1956 | J61: =Rebalance_Audit!S1956
A62: DJ30 | B62: 2024-03-29 | C62: DIA | D62: NVDA | E62: NVDA | F62: - | G62: =Rebalance_Audit!G2008 | H62: =Rebalance_Audit!Q2008 | I62: =Rebalance_Audit!R2008 | J62: =Rebalance_Audit!S2008
A63: DJ30 | B63: 2024-03-29 | C63: DIA | D63: IBM | E63: IBM | F63: - | G63: =Rebalance_Audit!G1999 | H63: =Rebalance_Audit!Q1999 | I63: =Rebalance_Audit!R1999 | J63: =Rebalance_Audit!S1999
A64: DJ30 | B64: 2024-03-29 | C64: DIA | D64: CAT | E64: CAT | F64: - | G64: =Rebalance_Audit!G1991 | H64: =Rebalance_Audit!Q1991 | I64: =Rebalance_Audit!R1991 | J64: =Rebalance_Audit!S1991
A65: DJ30 | B65: 2024-03-29 | C65: DIA | D65: CRM | E65: CRM | F65: - | G65: =Rebalance_Audit!G1992 | H65: =Rebalance_Audit!Q1992 | I65: =Rebalance_Audit!R1992 | J65: =Rebalance_Audit!S1992
A66: DJ30 | B66: 2024-03-29 | C66: DIA | D66: AMGN | E66: AMGN | F66: - | G66: =Rebalance_Audit!G1987 | H66: =Rebalance_Audit!Q1987 | I66: =Rebalance_Audit!R1987 | J66: =Rebalance_Audit!S1987
A67: DJ30 | B67: 2024-04-05 | C67: DIA | D67: NVDA | E67: NVDA | F67: - | G67: =Rebalance_Audit!G2039 | H67: =Rebalance_Audit!Q2039 | I67: =Rebalance_Audit!R2039 | J67: =Rebalance_Audit!S2039
A68: DJ30 | B68: 2024-04-05 | C68: DIA | D68: IBM | E68: IBM | F68: - | G68: =Rebalance_Audit!G2030 | H68: =Rebalance_Audit!Q2030 | I68: =Rebalance_Audit!R2030 | J68: =Rebalance_Audit!S2030
A69: DJ30 | B69: 2024-04-05 | C69: DIA | D69: CAT | E69: CAT | F69: - | G69: =Rebalance_Audit!G2022 | H69: =Rebalance_Audit!Q2022 | I69: =Rebalance_Audit!R2022 | J69: =Rebalance_Audit!S2022
A70: DJ30 | B70: 2024-04-05 | C70: DIA | D70: CRM | E70: CRM | F70: - | G70: =Rebalance_Audit!G2023 | H70: =Rebalance_Audit!Q2023 | I70: =Rebalance_Audit!R2023 | J70: =Rebalance_Audit!S2023
A71: DJ30 | B71: 2024-04-05 | C71: DIA | D71: AMGN | E71: AMGN | F71: - | G71: =Rebalance_Audit!G2018 | H71: =Rebalance_Audit!Q2018 | I71: =Rebalance_Audit!R2018 | J71: =Rebalance_Audit!S2018
A72: DJ30 | B72: 2024-04-12 | C72: DIA | D72: NVDA | E72: NVDA | F72: - | G72: =Rebalance_Audit!G2070 | H72: =Rebalance_Audit!Q2070 | I72: =Rebalance_Audit!R2070 | J72: =Rebalance_Audit!S2070
A73: DJ30 | B73: 2024-04-12 | C73: DIA | D73: IBM | E73: IBM | F73: - | G73: =Rebalance_Audit!G2061 | H73: =Rebalance_Audit!Q2061 | I73: =Rebalance_Audit!R2061 | J73: =Rebalance_Audit!S2061
A74: DJ30 | B74: 2024-04-12 | C74: DIA | D74: CAT | E74: CAT | F74: - | G74: =Rebalance_Audit!G2053 | H74: =Rebalance_Audit!Q2053 | I74: =Rebalance_Audit!R2053 | J74: =Rebalance_Audit!S2053
A75: DJ30 | B75: 2024-04-12 | C75: DIA | D75: CRM | E75: CRM | F75: - | G75: =Rebalance_Audit!G2054 | H75: =Rebalance_Audit!Q2054 | I75: =Rebalance_Audit!R2054 | J75: =Rebalance_Audit!S2054
A76: DJ30 | B76: 2024-04-12 | C76: DIA | D76: AMGN | E76: AMGN | F76: - | G76: =Rebalance_Audit!G2049 | H76: =Rebalance_Audit!Q2049 | I76: =Rebalance_Audit!R2049 | J76: =Rebalance_Audit!S2049
A77: DJ30 | B77: 2024-04-19 | C77: DIA | D77: NVDA | E77: NVDA | F77: - | G77: =Rebalance_Audit!G2101 | H77: =Rebalance_Audit!Q2101 | I77: =Rebalance_Audit!R2101 | J77: =Rebalance_Audit!S2101
A78: DJ30 | B78: 2024-04-19 | C78: DIA | D78: IBM | E78: IBM | F78: - | G78: =Rebalance_Audit!G2092 | H78: =Rebalance_Audit!Q2092 | I78: =Rebalance_Audit!R2092 | J78: =Rebalance_Audit!S2092
A79: DJ30 | B79: 2024-04-19 | C79: DIA | D79: CAT | E79: CAT | F79: - | G79: =Rebalance_Audit!G2084 | H79: =Rebalance_Audit!Q2084 | I79: =Rebalance_Audit!R2084 | J79: =Rebalance_Audit!S2084
A80: DJ30 | B80: 2024-04-19 | C80: DIA | D80: CRM | E80: CRM | F80: - | G80: =Rebalance_Audit!G2085 | H80: =Rebalance_Audit!Q2085 | I80: =Rebalance_Audit!R2085 | J80: =Rebalance_Audit!S2085
A81: DJ30 | B81: 2024-04-19 | C81: DIA | D81: JPM | E81: JPM | F81: - | G81: =Rebalance_Audit!G2094 | H81: =Rebalance_Audit!Q2094 | I81: =Rebalance_Audit!R2094 | J81: =Rebalance_Audit!S2094
A82: DJ30 | B82: 2024-04-26 | C82: DIA | D82: NVDA | E82: NVDA | F82: - | G82: =Rebalance_Audit!G2132 | H82: =Rebalance_Audit!Q2132 | I82: =Rebalance_Audit!R2132 | J82: =Rebalance_Audit!S2132
A83: DJ30 | B83: 2024-04-26 | C83: DIA | D83: IBM | E83: IBM | F83: - | G83: =Rebalance_Audit!G2123 | H83: =Rebalance_Audit!Q2123 | I83: =Rebalance_Audit!R2123 | J83: =Rebalance_Audit!S2123
A84: DJ30 | B84: 2024-04-26 | C84: DIA | D84: CAT | E84: CAT | F84: - | G84: =Rebalance_Audit!G2115 | H84: =Rebalance_Audit!Q2115 | I84: =Rebalance_Audit!R2115 | J84: =Rebalance_Audit!S2115
A85: DJ30 | B85: 2024-04-26 | C85: DIA | D85: CRM | E85: CRM | F85: - | G85: =Rebalance_Audit!G2116 | H85: =Rebalance_Audit!Q2116 | I85: =Rebalance_Audit!R2116 | J85: =Rebalance_Audit!S2116
A86: DJ30 | B86: 2024-04-26 | C86: DIA | D86: JPM | E86: JPM | F86: - | G86: =Rebalance_Audit!G2125 | H86: =Rebalance_Audit!Q2125 | I86: =Rebalance_Audit!R2125 | J86: =Rebalance_Audit!S2125
A87: DJ30 | B87: 2024-05-03 | C87: DIA | D87: NVDA | E87: NVDA | F87: - | G87: =Rebalance_Audit!G2163 | H87: =Rebalance_Audit!Q2163 | I87: =Rebalance_Audit!R2163 | J87: =Rebalance_Audit!S2163
A88: DJ30 | B88: 2024-05-03 | C88: DIA | D88: IBM | E88: IBM | F88: - | G88: =Rebalance_Audit!G2154 | H88: =Rebalance_Audit!Q2154 | I88: =Rebalance_Audit!R2154 | J88: =Rebalance_Audit!S2154
A89: DJ30 | B89: 2024-05-03 | C89: DIA | D89: CAT | E89: CAT | F89: - | G89: =Rebalance_Audit!G2146 | H89: =Rebalance_Audit!Q2146 | I89: =Rebalance_Audit!R2146 | J89: =Rebalance_Audit!S2146
A90: DJ30 | B90: 2024-05-03 | C90: DIA | D90: JPM | E90: JPM | F90: - | G90: =Rebalance_Audit!G2156 | H90: =Rebalance_Audit!Q2156 | I90: =Rebalance_Audit!R2156 | J90: =Rebalance_Audit!S2156
A91: DJ30 | B91: 2024-05-03 | C91: DIA | D91: CRM | E91: CRM | F91: - | G91: =Rebalance_Audit!G2147 | H91: =Rebalance_Audit!Q2147 | I91: =Rebalance_Audit!R2147 | J91: =Rebalance_Audit!S2147
A92: DJ30 | B92: 2024-05-10 | C92: DIA | D92: NVDA | E92: NVDA | F92: - | G92: =Rebalance_Audit!G2194 | H92: =Rebalance_Audit!Q2194 | I92: =Rebalance_Audit!R2194 | J92: =Rebalance_Audit!S2194
A93: DJ30 | B93: 2024-05-10 | C93: DIA | D93: IBM | E93: IBM | F93: - | G93: =Rebalance_Audit!G2185 | H93: =Rebalance_Audit!Q2185 | I93: =Rebalance_Audit!R2185 | J93: =Rebalance_Audit!S2185
A94: DJ30 | B94: 2024-05-10 | C94: DIA | D94: CAT | E94: CAT | F94: - | G94: =Rebalance_Audit!G2177 | H94: =Rebalance_Audit!Q2177 | I94: =Rebalance_Audit!R2177 | J94: =Rebalance_Audit!S2177
A95: DJ30 | B95: 2024-05-10 | C95: DIA | D95: JPM | E95: JPM | F95: - | G95: =Rebalance_Audit!G2187 | H95: =Rebalance_Audit!Q2187 | I95: =Rebalance_Audit!R2187 | J95: =Rebalance_Audit!S2187
A96: DJ30 | B96: 2024-05-10 | C96: DIA | D96: CRM | E96: CRM | F96: - | G96: =Rebalance_Audit!G2178 | H96: =Rebalance_Audit!Q2178 | I96: =Rebalance_Audit!R2178 | J96: =Rebalance_Audit!S2178
A97: DJ30 | B97: 2024-05-17 | C97: DIA | D97: NVDA | E97: NVDA | F97: - | G97: =Rebalance_Audit!G2225 | H97: =Rebalance_Audit!Q2225 | I97: =Rebalance_Audit!R2225 | J97: =Rebalance_Audit!S2225
A98: DJ30 | B98: 2024-05-17 | C98: DIA | D98: IBM | E98: IBM | F98: - | G98: =Rebalance_Audit!G2216 | H98: =Rebalance_Audit!Q2216 | I98: =Rebalance_Audit!R2216 | J98: =Rebalance_Audit!S2216
A99: DJ30 | B99: 2024-05-17 | C99: DIA | D99: CAT | E99: CAT | F99: - | G99: =Rebalance_Audit!G2208 | H99: =Rebalance_Audit!Q2208 | I99: =Rebalance_Audit!R2208 | J99: =Rebalance_Audit!S2208
A100: DJ30 | B100: 2024-05-17 | C100: DIA | D100: JPM | E100: JPM | F100: - | G100: =Rebalance_Audit!G2218 | H100: =Rebalance_Audit!Q2218 | I100: =Rebalance_Audit!R2218 | J100: =Rebalance_Audit!S2218
...
